{
    "students":

[{"id":1,"firstName":"Kristyn","lastName":"Gateley","dateBirth":"12/29/1999","sex":"F"},
{"id":2,"firstName":"Stanford","lastName":"Humfrey","dateBirth":"2/23/1996","sex":"M"},
{"id":3,"firstName":"Karrah","lastName":"Chese","dateBirth":"3/23/1994","sex":"F"},
{"id":4,"firstName":"Gar","lastName":"Josephs","dateBirth":"6/8/1997","sex":"M"},
{"id":5,"firstName":"Brandie","lastName":"Roughley","dateBirth":"2/9/1964","sex":"F"},
{"id":6,"firstName":"Naomi","lastName":"Necolds","dateBirth":"11/14/1906","sex":"F"},
{"id":7,"firstName":"Arlana","lastName":"Wharf","dateBirth":"2/27/1960","sex":"F"},
{"id":8,"firstName":"Babara","lastName":"Escudier","dateBirth":"7/19/1911","sex":"F"},
{"id":9,"firstName":"Alex","lastName":"Hallifax","dateBirth":"11/12/1994","sex":"F"},
{"id":10,"firstName":"Shirline","lastName":"MacNelly","dateBirth":"10/16/1923","sex":"F"},
{"id":11,"firstName":"Felisha","lastName":"Pinnijar","dateBirth":"4/12/1919","sex":"F"},
{"id":12,"firstName":"Rhett","lastName":"Landa","dateBirth":"5/17/1918","sex":"M"},
{"id":13,"firstName":"Kathi","lastName":"Mabson","dateBirth":"7/17/1996","sex":"F"},
{"id":14,"firstName":"Sergent","lastName":"Hanna","dateBirth":"3/14/1965","sex":"M"},
{"id":15,"firstName":"Etienne","lastName":"Antonsson","dateBirth":"3/16/1913","sex":"M"},
{"id":16,"firstName":"Noam","lastName":"Ambrogelli","dateBirth":"3/18/1939","sex":"M"},
{"id":17,"firstName":"Early","lastName":"Selesnick","dateBirth":"7/26/1941","sex":"M"},
{"id":18,"firstName":"Dyane","lastName":"Edison","dateBirth":"7/11/1958","sex":"F"},
{"id":19,"firstName":"Felice","lastName":"Sines","dateBirth":"11/13/1953","sex":"F"},
{"id":20,"firstName":"Eldridge","lastName":"Pym","dateBirth":"6/18/1931","sex":"M"},
{"id":21,"firstName":"Petr","lastName":"Snookes","dateBirth":"1/19/1959","sex":"M"},
{"id":22,"firstName":"Job","lastName":"Lambregts","dateBirth":"12/21/1987","sex":"M"},
{"id":23,"firstName":"Lilyan","lastName":"McIlheran","dateBirth":"5/15/2001","sex":"F"},
{"id":24,"firstName":"Torrin","lastName":"Willox","dateBirth":"5/15/1992","sex":"M"},
{"id":25,"firstName":"Les","lastName":"Mercey","dateBirth":"11/9/1924","sex":"M"},
{"id":26,"firstName":"Clive","lastName":"McLarnon","dateBirth":"11/6/1934","sex":"M"},
{"id":27,"firstName":"Gaile","lastName":"Kearford","dateBirth":"1/18/1951","sex":"M"},
{"id":28,"firstName":"Alford","lastName":"Surphliss","dateBirth":"5/18/2004","sex":"M"},
{"id":29,"firstName":"Gianni","lastName":"Punch","dateBirth":"12/7/1961","sex":"M"},
{"id":30,"firstName":"Dalenna","lastName":"Ference","dateBirth":"12/12/1957","sex":"F"},
{"id":31,"firstName":"Cherilynn","lastName":"Wraight","dateBirth":"5/11/1933","sex":"F"},
{"id":32,"firstName":"Neile","lastName":"Aleso","dateBirth":"2/21/1961","sex":"F"},
{"id":33,"firstName":"Gustave","lastName":"Gailor","dateBirth":"4/15/2003","sex":"M"},
{"id":34,"firstName":"Zilvia","lastName":"Itzkovici","dateBirth":"1/24/1954","sex":"F"},
{"id":35,"firstName":"Irvine","lastName":"Dance","dateBirth":"6/20/1911","sex":"M"},
{"id":36,"firstName":"Roselin","lastName":"Chidgey","dateBirth":"1/25/1906","sex":"F"},
{"id":37,"firstName":"Bald","lastName":"Pellman","dateBirth":"9/27/2000","sex":"M"},
{"id":38,"firstName":"Dulcea","lastName":"Piddlehinton","dateBirth":"3/1/1980","sex":"F"},
{"id":39,"firstName":"Skell","lastName":"Beyne","dateBirth":"2/11/1990","sex":"M"},
{"id":40,"firstName":"Ara","lastName":"Frohock","dateBirth":"1/19/1920","sex":"M"},
{"id":41,"firstName":"Corene","lastName":"Parbrook","dateBirth":"4/10/1998","sex":"F"},
{"id":42,"firstName":"Gwendolin","lastName":"Darton","dateBirth":"3/7/1919","sex":"F"},
{"id":43,"firstName":"Cirilo","lastName":"Deverson","dateBirth":"9/23/1975","sex":"M"},
{"id":44,"firstName":"Gretchen","lastName":"McAreavey","dateBirth":"12/10/1917","sex":"F"},
{"id":45,"firstName":"Natty","lastName":"Latimer","dateBirth":"9/18/1922","sex":"M"},
{"id":46,"firstName":"Petronia","lastName":"Lincke","dateBirth":"11/13/1996","sex":"F"},
{"id":47,"firstName":"Mohandas","lastName":"Sacchetti","dateBirth":"6/14/2002","sex":"M"},
{"id":48,"firstName":"Chadwick","lastName":"Kegley","dateBirth":"11/5/1907","sex":"M"},
{"id":49,"firstName":"Robby","lastName":"McKag","dateBirth":"10/12/1936","sex":"F"},
{"id":50,"firstName":"Lee","lastName":"Arne","dateBirth":"12/13/1988","sex":"F"},
{"id":51,"firstName":"Alyce","lastName":"Muat","dateBirth":"2/18/1915","sex":"F"},
{"id":52,"firstName":"Dov","lastName":"Szymanowski","dateBirth":"5/13/1942","sex":"M"},
{"id":53,"firstName":"Annelise","lastName":"O'Gormally","dateBirth":"1/7/1928","sex":"F"},
{"id":54,"firstName":"Rivalee","lastName":"Pavek","dateBirth":"12/16/1953","sex":"F"},
{"id":55,"firstName":"Leighton","lastName":"de Quesne","dateBirth":"1/27/1905","sex":"M"},
{"id":56,"firstName":"Tallou","lastName":"Djekic","dateBirth":"11/12/1949","sex":"F"},
{"id":57,"firstName":"Binni","lastName":"Gruby","dateBirth":"6/17/1978","sex":"F"},
{"id":58,"firstName":"Laverne","lastName":"Oliver","dateBirth":"6/15/1987","sex":"F"},
{"id":59,"firstName":"Lora","lastName":"Tomasian","dateBirth":"1/27/1956","sex":"F"},
{"id":60,"firstName":"Flore","lastName":"Paladini","dateBirth":"11/12/1906","sex":"F"},
{"id":61,"firstName":"Wally","lastName":"Nice","dateBirth":"9/10/1916","sex":"M"},
{"id":62,"firstName":"Thayne","lastName":"O'Hearn","dateBirth":"3/8/1979","sex":"M"},
{"id":63,"firstName":"Livvy","lastName":"Gentery","dateBirth":"5/17/1910","sex":"F"},
{"id":64,"firstName":"Pattin","lastName":"McLaren","dateBirth":"3/30/1949","sex":"M"},
{"id":65,"firstName":"Adrien","lastName":"Darben","dateBirth":"12/26/1907","sex":"M"},
{"id":66,"firstName":"Ariana","lastName":"Culverhouse","dateBirth":"8/16/1965","sex":"F"},
{"id":67,"firstName":"Onfroi","lastName":"Clitherow","dateBirth":"7/26/1954","sex":"M"},
{"id":68,"firstName":"Annemarie","lastName":"Meriton","dateBirth":"10/7/1918","sex":"F"},
{"id":69,"firstName":"Alaine","lastName":"Dehm","dateBirth":"12/7/1926","sex":"F"},
{"id":70,"firstName":"Jory","lastName":"Gentner","dateBirth":"11/16/1957","sex":"M"},
{"id":71,"firstName":"Cissiee","lastName":"Castello","dateBirth":"8/29/1943","sex":"F"},
{"id":72,"firstName":"Chaunce","lastName":"Peek","dateBirth":"12/25/1999","sex":"M"},
{"id":73,"firstName":"Phil","lastName":"Proom","dateBirth":"2/5/1992","sex":"F"},
{"id":74,"firstName":"Thom","lastName":"Mayoh","dateBirth":"6/28/1929","sex":"M"},
{"id":75,"firstName":"Ailis","lastName":"Skeete","dateBirth":"5/31/1926","sex":"F"},
{"id":76,"firstName":"Mandi","lastName":"Maroney","dateBirth":"7/23/1971","sex":"F"},
{"id":77,"firstName":"Lissa","lastName":"Szabo","dateBirth":"6/5/1958","sex":"F"},
{"id":78,"firstName":"Agustin","lastName":"Critchard","dateBirth":"11/5/1980","sex":"M"},
{"id":79,"firstName":"Obed","lastName":"Haryngton","dateBirth":"5/28/1907","sex":"M"},
{"id":80,"firstName":"Vonni","lastName":"Bonifas","dateBirth":"5/16/1937","sex":"F"},
{"id":81,"firstName":"Dean","lastName":"Cansdale","dateBirth":"7/28/1943","sex":"M"},
{"id":82,"firstName":"Jodee","lastName":"Sigart","dateBirth":"5/27/1916","sex":"F"},
{"id":83,"firstName":"Jedediah","lastName":"MacDavitt","dateBirth":"6/25/1938","sex":"M"},
{"id":84,"firstName":"Rab","lastName":"Huntly","dateBirth":"7/6/1964","sex":"M"},
{"id":85,"firstName":"Lynne","lastName":"Wolffers","dateBirth":"1/27/1956","sex":"F"},
{"id":86,"firstName":"Seward","lastName":"Alekhov","dateBirth":"5/5/1957","sex":"M"},
{"id":87,"firstName":"Dion","lastName":"Jakoubec","dateBirth":"1/7/1953","sex":"M"},
{"id":88,"firstName":"Lalo","lastName":"Sawle","dateBirth":"6/20/1966","sex":"M"},
{"id":89,"firstName":"Thom","lastName":"Dane","dateBirth":"12/22/1910","sex":"M"},
{"id":90,"firstName":"Alisa","lastName":"Coo","dateBirth":"12/24/1981","sex":"F"},
{"id":91,"firstName":"Wendell","lastName":"McGrouther","dateBirth":"10/28/1962","sex":"M"},
{"id":92,"firstName":"Ardine","lastName":"Pifford","dateBirth":"11/26/1961","sex":"F"},
{"id":93,"firstName":"Haywood","lastName":"Brockest","dateBirth":"4/12/2005","sex":"M"},
{"id":94,"firstName":"Cinnamon","lastName":"Burgis","dateBirth":"4/4/1971","sex":"F"},
{"id":95,"firstName":"Zorina","lastName":"Richings","dateBirth":"10/31/1951","sex":"F"},
{"id":96,"firstName":"Abbot","lastName":"Gladdis","dateBirth":"8/3/1998","sex":"M"},
{"id":97,"firstName":"Inger","lastName":"Lobbe","dateBirth":"4/17/1985","sex":"F"},
{"id":98,"firstName":"Mahmud","lastName":"Wait","dateBirth":"10/23/1907","sex":"M"},
{"id":99,"firstName":"Teodoro","lastName":"Lintott","dateBirth":"11/30/1943","sex":"M"},
{"id":100,"firstName":"Beverley","lastName":"Treble","dateBirth":"8/23/1942","sex":"F"},
{"id":101,"firstName":"Irita","lastName":"Mompesson","dateBirth":"10/23/1945","sex":"F"},
{"id":102,"firstName":"Klarrisa","lastName":"Riedel","dateBirth":"2/10/1910","sex":"F"},
{"id":103,"firstName":"Ariela","lastName":"Whitlock","dateBirth":"5/12/1946","sex":"F"},
{"id":104,"firstName":"Lezlie","lastName":"Critchlow","dateBirth":"2/7/1969","sex":"F"},
{"id":105,"firstName":"Hesther","lastName":"Duffield","dateBirth":"8/9/1969","sex":"F"},
{"id":106,"firstName":"Angelia","lastName":"Waddingham","dateBirth":"4/26/1977","sex":"F"},
{"id":107,"firstName":"Boonie","lastName":"Geldert","dateBirth":"2/1/1948","sex":"M"},
{"id":108,"firstName":"Ollie","lastName":"Laugier","dateBirth":"8/20/1949","sex":"M"},
{"id":109,"firstName":"Kinsley","lastName":"Godlip","dateBirth":"4/30/2003","sex":"M"},
{"id":110,"firstName":"Deane","lastName":"Goly","dateBirth":"12/26/1973","sex":"F"},
{"id":111,"firstName":"Kienan","lastName":"Drackford","dateBirth":"5/7/1930","sex":"M"},
{"id":112,"firstName":"Verne","lastName":"Ovenden","dateBirth":"4/27/1934","sex":"M"},
{"id":113,"firstName":"Hillie","lastName":"Viggers","dateBirth":"3/3/1915","sex":"M"},
{"id":114,"firstName":"Mario","lastName":"Isaksson","dateBirth":"10/8/1947","sex":"M"},
{"id":115,"firstName":"Cherida","lastName":"Ebbrell","dateBirth":"11/6/1996","sex":"F"},
{"id":116,"firstName":"Caleb","lastName":"Scading","dateBirth":"7/2/2002","sex":"M"},
{"id":117,"firstName":"Staffard","lastName":"Pavlenko","dateBirth":"2/27/1996","sex":"M"},
{"id":118,"firstName":"Cortney","lastName":"Danilovitch","dateBirth":"6/19/1954","sex":"F"},
{"id":119,"firstName":"Michel","lastName":"Mc Queen","dateBirth":"4/4/1997","sex":"M"},
{"id":120,"firstName":"Vonny","lastName":"Petch","dateBirth":"3/17/1929","sex":"F"},
{"id":121,"firstName":"Caryn","lastName":"Bortolazzi","dateBirth":"4/24/1917","sex":"F"},
{"id":122,"firstName":"Thorstein","lastName":"Padley","dateBirth":"8/28/1941","sex":"M"},
{"id":123,"firstName":"Fleming","lastName":"Trengrouse","dateBirth":"4/27/1964","sex":"M"},
{"id":124,"firstName":"Kristopher","lastName":"Terren","dateBirth":"5/20/1930","sex":"M"},
{"id":125,"firstName":"Valentino","lastName":"Ziemen","dateBirth":"4/17/1922","sex":"M"},
{"id":126,"firstName":"Guntar","lastName":"Bernardet","dateBirth":"3/16/1944","sex":"M"},
{"id":127,"firstName":"Jeri","lastName":"Tezure","dateBirth":"5/12/1981","sex":"F"},
{"id":128,"firstName":"Sammie","lastName":"Costard","dateBirth":"2/22/2004","sex":"M"},
{"id":129,"firstName":"Olimpia","lastName":"Moulin","dateBirth":"9/9/1929","sex":"F"},
{"id":130,"firstName":"Huntley","lastName":"Spadari","dateBirth":"11/20/2001","sex":"M"},
{"id":131,"firstName":"Blinnie","lastName":"Hordle","dateBirth":"2/3/1990","sex":"F"},
{"id":132,"firstName":"Menard","lastName":"Broadwood","dateBirth":"12/22/1999","sex":"M"},
{"id":133,"firstName":"Celina","lastName":"Ottee","dateBirth":"3/27/1923","sex":"F"},
{"id":134,"firstName":"Billy","lastName":"Cawson","dateBirth":"3/25/1939","sex":"M"},
{"id":135,"firstName":"Munmro","lastName":"Chamney","dateBirth":"10/11/1990","sex":"M"},
{"id":136,"firstName":"Byran","lastName":"Setterthwait","dateBirth":"12/21/1932","sex":"M"},
{"id":137,"firstName":"Bertrand","lastName":"Radke","dateBirth":"8/31/1913","sex":"M"},
{"id":138,"firstName":"Myrtice","lastName":"Escoffier","dateBirth":"2/23/1985","sex":"F"},
{"id":139,"firstName":"Jimmie","lastName":"Cothey","dateBirth":"12/11/1993","sex":"M"},
{"id":140,"firstName":"Denney","lastName":"Tapply","dateBirth":"12/30/2002","sex":"M"},
{"id":141,"firstName":"Morie","lastName":"Leat","dateBirth":"5/4/1992","sex":"M"},
{"id":142,"firstName":"Anatollo","lastName":"Mackness","dateBirth":"5/2/1952","sex":"M"},
{"id":143,"firstName":"Shela","lastName":"Whorton","dateBirth":"1/9/1947","sex":"F"},
{"id":144,"firstName":"Desirae","lastName":"Ansty","dateBirth":"12/23/1925","sex":"F"},
{"id":145,"firstName":"Cart","lastName":"Lacer","dateBirth":"2/15/1999","sex":"M"},
{"id":146,"firstName":"Blake","lastName":"Emery","dateBirth":"9/24/1996","sex":"M"},
{"id":147,"firstName":"Sutherland","lastName":"Blight","dateBirth":"5/7/1933","sex":"M"},
{"id":148,"firstName":"Klement","lastName":"Gong","dateBirth":"6/28/1970","sex":"M"},
{"id":149,"firstName":"Lissa","lastName":"Jamary","dateBirth":"12/26/2005","sex":"F"},
{"id":150,"firstName":"Stephanie","lastName":"Borth","dateBirth":"12/31/1910","sex":"F"},
{"id":151,"firstName":"Nert","lastName":"Radborn","dateBirth":"11/12/1966","sex":"F"},
{"id":152,"firstName":"Hazel","lastName":"Swetland","dateBirth":"11/13/1997","sex":"F"},
{"id":153,"firstName":"Persis","lastName":"Baldery","dateBirth":"9/17/1999","sex":"F"},
{"id":154,"firstName":"Karleen","lastName":"Linbohm","dateBirth":"7/1/1967","sex":"F"},
{"id":155,"firstName":"Donovan","lastName":"Titchard","dateBirth":"7/2/1915","sex":"M"},
{"id":156,"firstName":"Jennifer","lastName":"Lankford","dateBirth":"11/2/1908","sex":"F"},
{"id":157,"firstName":"Evin","lastName":"Martinets","dateBirth":"4/24/1907","sex":"M"},
{"id":158,"firstName":"Jeremias","lastName":"Le Pruvost","dateBirth":"8/9/1943","sex":"M"},
{"id":159,"firstName":"Kendricks","lastName":"Hutt","dateBirth":"3/6/1909","sex":"M"},
{"id":160,"firstName":"Isadora","lastName":"Dagleas","dateBirth":"7/20/1928","sex":"F"},
{"id":161,"firstName":"Chance","lastName":"Yakhin","dateBirth":"3/29/1972","sex":"M"},
{"id":162,"firstName":"Harriot","lastName":"Colthurst","dateBirth":"6/19/1914","sex":"F"},
{"id":163,"firstName":"Dannie","lastName":"Edon","dateBirth":"10/2/1924","sex":"M"},
{"id":164,"firstName":"Clayson","lastName":"Kyllford","dateBirth":"3/31/1916","sex":"M"},
{"id":165,"firstName":"Christian","lastName":"Whatman","dateBirth":"6/12/1937","sex":"M"},
{"id":166,"firstName":"Shelley","lastName":"Witcher","dateBirth":"1/29/1995","sex":"F"},
{"id":167,"firstName":"Saraann","lastName":"Hinze","dateBirth":"8/5/1933","sex":"F"},
{"id":168,"firstName":"Grant","lastName":"D'Agostino","dateBirth":"9/2/1928","sex":"M"},
{"id":169,"firstName":"Arthur","lastName":"Dalgliesh","dateBirth":"4/8/1994","sex":"M"},
{"id":170,"firstName":"Clerkclaude","lastName":"Caulcutt","dateBirth":"12/27/1909","sex":"M"},
{"id":171,"firstName":"Keelia","lastName":"Dofty","dateBirth":"2/14/1914","sex":"F"},
{"id":172,"firstName":"Hortense","lastName":"Keerl","dateBirth":"4/23/1983","sex":"F"},
{"id":173,"firstName":"Kacy","lastName":"Jeavon","dateBirth":"3/29/1948","sex":"F"},
{"id":174,"firstName":"Opalina","lastName":"Millar","dateBirth":"5/10/1906","sex":"F"},
{"id":175,"firstName":"Vite","lastName":"Wight","dateBirth":"8/23/1983","sex":"M"},
{"id":176,"firstName":"Cleveland","lastName":"Kellet","dateBirth":"10/1/1999","sex":"M"},
{"id":177,"firstName":"Putnem","lastName":"Vido","dateBirth":"1/20/2001","sex":"M"},
{"id":178,"firstName":"Lorens","lastName":"Deguara","dateBirth":"12/13/1938","sex":"M"},
{"id":179,"firstName":"Pietrek","lastName":"Marcq","dateBirth":"6/28/1993","sex":"M"},
{"id":180,"firstName":"Kendal","lastName":"Burnitt","dateBirth":"9/15/1913","sex":"M"},
{"id":181,"firstName":"Rafaellle","lastName":"Tash","dateBirth":"6/2/1942","sex":"M"},
{"id":182,"firstName":"Neale","lastName":"Musgrove","dateBirth":"11/9/1942","sex":"M"},
{"id":183,"firstName":"Friedrich","lastName":"Dackombe","dateBirth":"10/12/1920","sex":"M"},
{"id":184,"firstName":"Arnaldo","lastName":"Kears","dateBirth":"5/27/1928","sex":"M"},
{"id":185,"firstName":"Quincey","lastName":"Jagiela","dateBirth":"1/2/1918","sex":"M"},
{"id":186,"firstName":"Kelbee","lastName":"Utley","dateBirth":"11/15/2001","sex":"M"},
{"id":187,"firstName":"Belvia","lastName":"Morlon","dateBirth":"7/11/1915","sex":"F"},
{"id":188,"firstName":"Justin","lastName":"Legat","dateBirth":"3/10/1915","sex":"M"},
{"id":189,"firstName":"Falito","lastName":"Rubanenko","dateBirth":"8/19/1937","sex":"M"},
{"id":190,"firstName":"Reuben","lastName":"Makiver","dateBirth":"8/23/2001","sex":"M"},
{"id":191,"firstName":"Pepi","lastName":"Roggieri","dateBirth":"4/21/1980","sex":"F"},
{"id":192,"firstName":"Darbee","lastName":"Geraldez","dateBirth":"8/3/1951","sex":"M"},
{"id":193,"firstName":"Henrik","lastName":"Mitchely","dateBirth":"12/25/2003","sex":"M"},
{"id":194,"firstName":"Zane","lastName":"Loadman","dateBirth":"9/18/1939","sex":"M"},
{"id":195,"firstName":"Trev","lastName":"Beattie","dateBirth":"2/27/1920","sex":"M"},
{"id":196,"firstName":"Corine","lastName":"Santry","dateBirth":"4/14/1945","sex":"F"},
{"id":197,"firstName":"Valera","lastName":"Isherwood","dateBirth":"12/31/1976","sex":"F"},
{"id":198,"firstName":"Willamina","lastName":"Wride","dateBirth":"6/16/1981","sex":"F"},
{"id":199,"firstName":"Karyn","lastName":"Krishtopaittis","dateBirth":"5/6/1968","sex":"F"},
{"id":200,"firstName":"Anni","lastName":"Lyver","dateBirth":"9/7/1914","sex":"F"},
{"id":201,"firstName":"Alena","lastName":"Pattison","dateBirth":"11/9/1906","sex":"F"},
{"id":202,"firstName":"Ara","lastName":"Kemery","dateBirth":"6/15/1964","sex":"F"},
{"id":203,"firstName":"Michal","lastName":"Epple","dateBirth":"3/22/2005","sex":"F"},
{"id":204,"firstName":"Lilah","lastName":"Pietron","dateBirth":"11/7/1941","sex":"F"},
{"id":205,"firstName":"Maire","lastName":"Blakiston","dateBirth":"10/24/1944","sex":"F"},
{"id":206,"firstName":"Tripp","lastName":"Briatt","dateBirth":"4/1/1913","sex":"M"},
{"id":207,"firstName":"Menard","lastName":"Rambaut","dateBirth":"9/26/2005","sex":"M"},
{"id":208,"firstName":"Willey","lastName":"Rowcastle","dateBirth":"4/2/1918","sex":"M"},
{"id":209,"firstName":"Shoshanna","lastName":"Gee","dateBirth":"9/4/1956","sex":"F"},
{"id":210,"firstName":"Freddy","lastName":"Baggs","dateBirth":"3/14/1987","sex":"F"},
{"id":211,"firstName":"Sibylle","lastName":"Burgess","dateBirth":"7/27/1971","sex":"F"},
{"id":212,"firstName":"Efren","lastName":"Goody","dateBirth":"3/10/1931","sex":"M"},
{"id":213,"firstName":"Wynn","lastName":"Goodbarne","dateBirth":"6/28/1971","sex":"F"},
{"id":214,"firstName":"Gretna","lastName":"Kareman","dateBirth":"2/23/1966","sex":"F"},
{"id":215,"firstName":"Benjamin","lastName":"Overstone","dateBirth":"8/20/1966","sex":"M"},
{"id":216,"firstName":"Ephraim","lastName":"Brockley","dateBirth":"11/19/1955","sex":"M"},
{"id":217,"firstName":"Ardella","lastName":"Wortt","dateBirth":"11/9/1963","sex":"F"},
{"id":218,"firstName":"Garvin","lastName":"Edwinson","dateBirth":"9/23/2001","sex":"M"},
{"id":219,"firstName":"Jojo","lastName":"Pindred","dateBirth":"4/25/1954","sex":"F"},
{"id":220,"firstName":"Giselbert","lastName":"Smeuin","dateBirth":"7/26/1944","sex":"M"},
{"id":221,"firstName":"Fredek","lastName":"Doak","dateBirth":"11/11/1976","sex":"M"},
{"id":222,"firstName":"Clifford","lastName":"Worlock","dateBirth":"10/27/1933","sex":"M"},
{"id":223,"firstName":"Anna-diane","lastName":"Diegan","dateBirth":"3/5/1931","sex":"F"},
{"id":224,"firstName":"Saidee","lastName":"Rattry","dateBirth":"3/9/1926","sex":"F"},
{"id":225,"firstName":"Deni","lastName":"Kunz","dateBirth":"11/7/1945","sex":"F"},
{"id":226,"firstName":"Isidro","lastName":"McAlinion","dateBirth":"10/24/1937","sex":"M"},
{"id":227,"firstName":"Kati","lastName":"D'Aeth","dateBirth":"5/6/1952","sex":"F"},
{"id":228,"firstName":"Ardenia","lastName":"Woolerton","dateBirth":"11/1/1996","sex":"F"},
{"id":229,"firstName":"Silvio","lastName":"Hatfield","dateBirth":"8/22/1955","sex":"M"},
{"id":230,"firstName":"Corabella","lastName":"Fossick","dateBirth":"9/8/1907","sex":"F"},
{"id":231,"firstName":"Davita","lastName":"Parkisson","dateBirth":"9/30/1923","sex":"F"},
{"id":232,"firstName":"Georgina","lastName":"Cocke","dateBirth":"8/17/1998","sex":"F"},
{"id":233,"firstName":"Kile","lastName":"Khadir","dateBirth":"7/14/2001","sex":"M"},
{"id":234,"firstName":"Barbe","lastName":"Tomsa","dateBirth":"4/21/1915","sex":"F"},
{"id":235,"firstName":"Godfry","lastName":"Goodisson","dateBirth":"5/20/1968","sex":"M"},
{"id":236,"firstName":"Tomaso","lastName":"Stickells","dateBirth":"12/17/1945","sex":"M"},
{"id":237,"firstName":"Mamie","lastName":"Patience","dateBirth":"3/19/1974","sex":"F"},
{"id":238,"firstName":"Georg","lastName":"Mouland","dateBirth":"2/13/1913","sex":"M"},
{"id":239,"firstName":"Reinald","lastName":"Wheelhouse","dateBirth":"5/12/1905","sex":"M"},
{"id":240,"firstName":"Paule","lastName":"Claringbold","dateBirth":"4/20/1994","sex":"F"},
{"id":241,"firstName":"Mac","lastName":"Bacchus","dateBirth":"1/3/1922","sex":"M"},
{"id":242,"firstName":"Grannie","lastName":"Sheahan","dateBirth":"9/14/1945","sex":"M"},
{"id":243,"firstName":"Freeman","lastName":"Busst","dateBirth":"6/13/1954","sex":"M"},
{"id":244,"firstName":"Drew","lastName":"Jephson","dateBirth":"12/31/1921","sex":"M"},
{"id":245,"firstName":"Alia","lastName":"Fotherby","dateBirth":"7/17/1968","sex":"F"},
{"id":246,"firstName":"Carroll","lastName":"Possa","dateBirth":"10/25/1926","sex":"M"},
{"id":247,"firstName":"Barnabe","lastName":"Longfut","dateBirth":"7/26/1937","sex":"M"},
{"id":248,"firstName":"Cleveland","lastName":"Pittel","dateBirth":"8/27/1956","sex":"M"},
{"id":249,"firstName":"Linoel","lastName":"Stuckey","dateBirth":"6/3/1986","sex":"M"},
{"id":250,"firstName":"Shoshana","lastName":"Emmer","dateBirth":"10/6/2003","sex":"F"},
{"id":251,"firstName":"Clay","lastName":"Yaakov","dateBirth":"5/3/1964","sex":"M"},
{"id":252,"firstName":"Mariann","lastName":"Archanbault","dateBirth":"12/30/1920","sex":"F"},
{"id":253,"firstName":"Kristel","lastName":"Lodwig","dateBirth":"5/20/1919","sex":"F"},
{"id":254,"firstName":"Claybourne","lastName":"Iwanczyk","dateBirth":"6/16/1953","sex":"M"},
{"id":255,"firstName":"Zollie","lastName":"Demeter","dateBirth":"1/14/1992","sex":"M"},
{"id":256,"firstName":"Charlton","lastName":"Balser","dateBirth":"4/14/1936","sex":"M"},
{"id":257,"firstName":"Barnett","lastName":"Danks","dateBirth":"10/21/1996","sex":"M"},
{"id":258,"firstName":"Ami","lastName":"Bigglestone","dateBirth":"9/26/1992","sex":"F"},
{"id":259,"firstName":"Carolynn","lastName":"McCluin","dateBirth":"1/14/1946","sex":"F"},
{"id":260,"firstName":"Burke","lastName":"Newson","dateBirth":"2/27/1926","sex":"M"},
{"id":261,"firstName":"Katrine","lastName":"Hatch","dateBirth":"1/10/1921","sex":"F"},
{"id":262,"firstName":"Moreen","lastName":"Wathen","dateBirth":"1/10/1955","sex":"F"},
{"id":263,"firstName":"Shirley","lastName":"Eastmead","dateBirth":"5/29/1942","sex":"F"},
{"id":264,"firstName":"Aldus","lastName":"Cracoe","dateBirth":"6/12/1913","sex":"M"},
{"id":265,"firstName":"Judd","lastName":"Jobbing","dateBirth":"3/10/1990","sex":"M"},
{"id":266,"firstName":"Taylor","lastName":"McKeighan","dateBirth":"9/1/1965","sex":"M"},
{"id":267,"firstName":"Emmerich","lastName":"Mandel","dateBirth":"7/30/1967","sex":"M"},
{"id":268,"firstName":"Heddie","lastName":"Chang","dateBirth":"1/5/1950","sex":"F"},
{"id":269,"firstName":"Harlan","lastName":"Beelby","dateBirth":"9/7/1962","sex":"M"},
{"id":270,"firstName":"Sophia","lastName":"Sexti","dateBirth":"7/11/2003","sex":"F"},
{"id":271,"firstName":"Wash","lastName":"Chrystie","dateBirth":"7/16/2000","sex":"M"},
{"id":272,"firstName":"Irving","lastName":"Durant","dateBirth":"2/28/1965","sex":"M"},
{"id":273,"firstName":"Nealon","lastName":"Pittel","dateBirth":"2/10/1906","sex":"M"},
{"id":274,"firstName":"Caryn","lastName":"MacCague","dateBirth":"4/9/1920","sex":"F"},
{"id":275,"firstName":"Tildi","lastName":"Peschmann","dateBirth":"2/5/1944","sex":"F"},
{"id":276,"firstName":"Barnabe","lastName":"Heyward","dateBirth":"3/9/1930","sex":"M"},
{"id":277,"firstName":"Tobias","lastName":"Mcwhinnie","dateBirth":"2/12/1927","sex":"M"},
{"id":278,"firstName":"Bryana","lastName":"Matfin","dateBirth":"5/16/1968","sex":"F"},
{"id":279,"firstName":"Forrest","lastName":"Toe","dateBirth":"9/25/1945","sex":"M"},
{"id":280,"firstName":"Genia","lastName":"Maginot","dateBirth":"7/21/1935","sex":"F"},
{"id":281,"firstName":"Armand","lastName":"Rowlett","dateBirth":"9/27/1971","sex":"M"},
{"id":282,"firstName":"Bili","lastName":"Jenyns","dateBirth":"9/30/1943","sex":"F"},
{"id":283,"firstName":"Amandi","lastName":"Tarbett","dateBirth":"1/8/1921","sex":"F"},
{"id":284,"firstName":"Rhoda","lastName":"Askell","dateBirth":"9/27/1956","sex":"F"},
{"id":285,"firstName":"Cord","lastName":"Clemencet","dateBirth":"3/27/1914","sex":"M"},
{"id":286,"firstName":"Sibel","lastName":"Willavize","dateBirth":"7/10/1932","sex":"F"},
{"id":287,"firstName":"Lissie","lastName":"Hazel","dateBirth":"7/11/1964","sex":"F"},
{"id":288,"firstName":"Corilla","lastName":"Switsur","dateBirth":"10/24/1906","sex":"F"},
{"id":289,"firstName":"Benedict","lastName":"Melmar","dateBirth":"1/22/1915","sex":"M"},
{"id":290,"firstName":"Sharla","lastName":"Shimon","dateBirth":"4/3/2005","sex":"F"},
{"id":291,"firstName":"Bambie","lastName":"Batchelor","dateBirth":"2/15/1990","sex":"F"},
{"id":292,"firstName":"Saraann","lastName":"Maddern","dateBirth":"8/28/2001","sex":"F"},
{"id":293,"firstName":"Coop","lastName":"Pavia","dateBirth":"7/18/1987","sex":"M"},
{"id":294,"firstName":"Chrissy","lastName":"Ruos","dateBirth":"12/6/1916","sex":"F"},
{"id":295,"firstName":"Editha","lastName":"Stonman","dateBirth":"1/8/1928","sex":"F"},
{"id":296,"firstName":"Carol-jean","lastName":"Connolly","dateBirth":"12/2/1970","sex":"F"},
{"id":297,"firstName":"Huberto","lastName":"Cotterrill","dateBirth":"9/11/1978","sex":"M"},
{"id":298,"firstName":"Esmaria","lastName":"Harse","dateBirth":"2/6/1952","sex":"F"},
{"id":299,"firstName":"Flory","lastName":"Demelt","dateBirth":"6/22/1979","sex":"M"},
{"id":300,"firstName":"Stevie","lastName":"McKinlay","dateBirth":"3/16/1923","sex":"M"},
{"id":301,"firstName":"Larine","lastName":"Eastway","dateBirth":"2/28/2005","sex":"F"},
{"id":302,"firstName":"Viki","lastName":"Emor","dateBirth":"10/31/1954","sex":"F"},
{"id":303,"firstName":"Melinde","lastName":"Catterson","dateBirth":"2/25/1949","sex":"F"},
{"id":304,"firstName":"Kristy","lastName":"Demcik","dateBirth":"5/1/1921","sex":"F"},
{"id":305,"firstName":"Paquito","lastName":"Ratcliff","dateBirth":"11/28/1990","sex":"M"},
{"id":306,"firstName":"Meggie","lastName":"Cranham","dateBirth":"9/24/1953","sex":"F"},
{"id":307,"firstName":"Phylis","lastName":"Duinkerk","dateBirth":"8/18/1975","sex":"F"},
{"id":308,"firstName":"Eldin","lastName":"Betjes","dateBirth":"2/4/1929","sex":"M"},
{"id":309,"firstName":"Dillie","lastName":"Laval","dateBirth":"9/18/1978","sex":"M"},
{"id":310,"firstName":"Archy","lastName":"Cleal","dateBirth":"2/4/1932","sex":"M"},
{"id":311,"firstName":"Goldie","lastName":"Franscioni","dateBirth":"7/21/1950","sex":"F"},
{"id":312,"firstName":"Rick","lastName":"Knudsen","dateBirth":"12/12/1995","sex":"M"},
{"id":313,"firstName":"Jeralee","lastName":"Brady","dateBirth":"2/27/1994","sex":"F"},
{"id":314,"firstName":"Lissa","lastName":"Pendry","dateBirth":"1/17/2004","sex":"F"},
{"id":315,"firstName":"Jeno","lastName":"Pressnell","dateBirth":"8/8/1955","sex":"M"},
{"id":316,"firstName":"Janos","lastName":"Maddie","dateBirth":"10/4/1978","sex":"M"},
{"id":317,"firstName":"Beale","lastName":"Barbara","dateBirth":"8/3/1945","sex":"M"},
{"id":318,"firstName":"Barnard","lastName":"Danielsen","dateBirth":"12/4/1934","sex":"M"},
{"id":319,"firstName":"Sissie","lastName":"Maciocia","dateBirth":"9/13/1957","sex":"F"},
{"id":320,"firstName":"Panchito","lastName":"Vennings","dateBirth":"7/12/1935","sex":"M"},
{"id":321,"firstName":"Rosa","lastName":"Morpeth","dateBirth":"10/16/1999","sex":"F"},
{"id":322,"firstName":"Nichols","lastName":"Egginton","dateBirth":"12/21/1948","sex":"M"},
{"id":323,"firstName":"Morgan","lastName":"Saterthwait","dateBirth":"8/7/1906","sex":"F"},
{"id":324,"firstName":"Saloma","lastName":"McBride","dateBirth":"7/28/1916","sex":"F"},
{"id":325,"firstName":"Nichole","lastName":"Vause","dateBirth":"11/21/1922","sex":"M"},
{"id":326,"firstName":"Torrey","lastName":"Alekhov","dateBirth":"6/1/1965","sex":"M"},
{"id":327,"firstName":"Clair","lastName":"Nilles","dateBirth":"4/4/1997","sex":"M"},
{"id":328,"firstName":"Josselyn","lastName":"Jurgensen","dateBirth":"10/17/2002","sex":"F"},
{"id":329,"firstName":"Ginger","lastName":"Reckhouse","dateBirth":"8/30/1989","sex":"M"},
{"id":330,"firstName":"Valry","lastName":"McGurgan","dateBirth":"4/16/1965","sex":"F"},
{"id":331,"firstName":"Annaliese","lastName":"Haynes","dateBirth":"9/18/1992","sex":"F"},
{"id":332,"firstName":"Winslow","lastName":"Bernocchi","dateBirth":"2/25/1966","sex":"M"},
{"id":333,"firstName":"Hinze","lastName":"Giovanni","dateBirth":"2/3/1970","sex":"M"},
{"id":334,"firstName":"Antoinette","lastName":"Kealy","dateBirth":"9/19/1910","sex":"F"},
{"id":335,"firstName":"Jessalyn","lastName":"Geill","dateBirth":"5/26/1946","sex":"F"},
{"id":336,"firstName":"Ann","lastName":"Piatkow","dateBirth":"5/5/1965","sex":"F"},
{"id":337,"firstName":"Melisandra","lastName":"Nelthropp","dateBirth":"3/19/1911","sex":"F"},
{"id":338,"firstName":"Fulvia","lastName":"Kikke","dateBirth":"3/27/1956","sex":"F"},
{"id":339,"firstName":"Latrina","lastName":"Draper","dateBirth":"6/23/1910","sex":"F"},
{"id":340,"firstName":"Loren","lastName":"Goudman","dateBirth":"11/23/2000","sex":"M"},
{"id":341,"firstName":"Nancee","lastName":"Pyrke","dateBirth":"11/13/1925","sex":"F"},
{"id":342,"firstName":"Ezra","lastName":"Smallpeice","dateBirth":"7/17/1958","sex":"M"},
{"id":343,"firstName":"Hinze","lastName":"Bone","dateBirth":"7/30/1912","sex":"M"},
{"id":344,"firstName":"Rorie","lastName":"Seeler","dateBirth":"11/18/1995","sex":"F"},
{"id":345,"firstName":"Ginny","lastName":"Line","dateBirth":"8/17/1953","sex":"F"},
{"id":346,"firstName":"Grayce","lastName":"Doolan","dateBirth":"10/19/1914","sex":"F"},
{"id":347,"firstName":"Helaina","lastName":"Cajkler","dateBirth":"12/16/1945","sex":"F"},
{"id":348,"firstName":"Terrye","lastName":"Sherewood","dateBirth":"8/11/1922","sex":"F"},
{"id":349,"firstName":"Carlye","lastName":"Croneen","dateBirth":"6/23/1987","sex":"F"},
{"id":350,"firstName":"Arney","lastName":"Tripe","dateBirth":"1/20/1949","sex":"M"},
{"id":351,"firstName":"Skelly","lastName":"McGrudder","dateBirth":"10/3/1966","sex":"M"},
{"id":352,"firstName":"Germain","lastName":"Driscoll","dateBirth":"12/21/1971","sex":"M"},
{"id":353,"firstName":"Kalinda","lastName":"Chieze","dateBirth":"10/18/1919","sex":"F"},
{"id":354,"firstName":"Cloe","lastName":"Cantrell","dateBirth":"2/9/1985","sex":"F"},
{"id":355,"firstName":"Derek","lastName":"Takis","dateBirth":"8/25/1906","sex":"M"},
{"id":356,"firstName":"Tome","lastName":"Streeter","dateBirth":"5/5/1996","sex":"M"},
{"id":357,"firstName":"Manda","lastName":"Elsmere","dateBirth":"5/2/1992","sex":"F"},
{"id":358,"firstName":"Cornelia","lastName":"Boyde","dateBirth":"7/27/1907","sex":"F"},
{"id":359,"firstName":"Clevey","lastName":"D'eye","dateBirth":"6/12/1962","sex":"M"},
{"id":360,"firstName":"Coletta","lastName":"Greenalf","dateBirth":"9/25/1971","sex":"F"},
{"id":361,"firstName":"Modesty","lastName":"McIndoe","dateBirth":"9/19/1930","sex":"F"},
{"id":362,"firstName":"Ophelie","lastName":"Sauvan","dateBirth":"5/15/1914","sex":"F"},
{"id":363,"firstName":"Cordey","lastName":"Basey","dateBirth":"6/1/1983","sex":"F"},
{"id":364,"firstName":"Vivyanne","lastName":"Gair","dateBirth":"7/11/1944","sex":"F"},
{"id":365,"firstName":"Alysa","lastName":"Mears","dateBirth":"10/24/1942","sex":"F"},
{"id":366,"firstName":"Normand","lastName":"Hardcastle","dateBirth":"7/5/1909","sex":"M"},
{"id":367,"firstName":"Olva","lastName":"Telling","dateBirth":"1/21/1905","sex":"F"},
{"id":368,"firstName":"Ansley","lastName":"Olivetta","dateBirth":"12/25/2005","sex":"F"},
{"id":369,"firstName":"Molli","lastName":"Bachnic","dateBirth":"6/11/2003","sex":"F"},
{"id":370,"firstName":"Hersh","lastName":"Pagnin","dateBirth":"4/28/1972","sex":"M"},
{"id":371,"firstName":"Eva","lastName":"Cull","dateBirth":"9/15/1922","sex":"F"},
{"id":372,"firstName":"Welby","lastName":"Shakespear","dateBirth":"12/7/1908","sex":"M"},
{"id":373,"firstName":"Barbabas","lastName":"Priddey","dateBirth":"9/8/1915","sex":"M"},
{"id":374,"firstName":"Modestia","lastName":"Legonidec","dateBirth":"11/3/1926","sex":"F"},
{"id":375,"firstName":"Hershel","lastName":"Mumbeson","dateBirth":"7/11/1973","sex":"M"},
{"id":376,"firstName":"Magda","lastName":"Ethington","dateBirth":"8/28/1953","sex":"F"},
{"id":377,"firstName":"Maryanna","lastName":"Dearle","dateBirth":"7/16/1949","sex":"F"},
{"id":378,"firstName":"Raimondo","lastName":"Lord","dateBirth":"4/12/1917","sex":"M"},
{"id":379,"firstName":"Terrel","lastName":"Houlridge","dateBirth":"4/5/1923","sex":"M"},
{"id":380,"firstName":"Cortie","lastName":"Serjent","dateBirth":"10/12/1997","sex":"M"},
{"id":381,"firstName":"Colan","lastName":"Turn","dateBirth":"10/30/1956","sex":"M"},
{"id":382,"firstName":"Corrie","lastName":"MacRory","dateBirth":"7/29/1945","sex":"F"},
{"id":383,"firstName":"Gustav","lastName":"Altree","dateBirth":"2/6/1963","sex":"M"},
{"id":384,"firstName":"Conny","lastName":"De Cruce","dateBirth":"1/3/1960","sex":"M"},
{"id":385,"firstName":"Andie","lastName":"Jerrold","dateBirth":"1/10/1948","sex":"F"},
{"id":386,"firstName":"Rafaelita","lastName":"Ingleton","dateBirth":"10/29/1936","sex":"F"},
{"id":387,"firstName":"Mandi","lastName":"Jevon","dateBirth":"11/20/1908","sex":"F"},
{"id":388,"firstName":"Consuela","lastName":"Vasnetsov","dateBirth":"9/5/1950","sex":"F"},
{"id":389,"firstName":"Case","lastName":"Taborre","dateBirth":"6/20/1945","sex":"M"},
{"id":390,"firstName":"Fifi","lastName":"Garthshore","dateBirth":"5/2/1922","sex":"F"},
{"id":391,"firstName":"Larine","lastName":"Kielt","dateBirth":"11/25/1958","sex":"F"},
{"id":392,"firstName":"Elga","lastName":"Habershon","dateBirth":"5/25/1919","sex":"F"},
{"id":393,"firstName":"Amalia","lastName":"Jakubowsky","dateBirth":"1/24/1921","sex":"F"},
{"id":394,"firstName":"Calida","lastName":"Onn","dateBirth":"4/13/1990","sex":"F"},
{"id":395,"firstName":"Isa","lastName":"Zealy","dateBirth":"12/28/1933","sex":"F"},
{"id":396,"firstName":"Amelia","lastName":"Newlands","dateBirth":"8/12/1924","sex":"F"},
{"id":397,"firstName":"Archibald","lastName":"By","dateBirth":"6/22/1967","sex":"M"},
{"id":398,"firstName":"Pip","lastName":"MacFarlan","dateBirth":"7/18/1911","sex":"M"},
{"id":399,"firstName":"Cairistiona","lastName":"Guerreiro","dateBirth":"5/27/1983","sex":"F"},
{"id":400,"firstName":"Cedric","lastName":"Giraudo","dateBirth":"2/17/1927","sex":"M"},
{"id":401,"firstName":"Piper","lastName":"Batten","dateBirth":"5/25/1942","sex":"F"},
{"id":402,"firstName":"Alberik","lastName":"Jedrzejczak","dateBirth":"9/2/1983","sex":"M"},
{"id":403,"firstName":"Emilio","lastName":"Stanyon","dateBirth":"10/18/1967","sex":"M"},
{"id":404,"firstName":"Royce","lastName":"Monelle","dateBirth":"1/4/1946","sex":"M"},
{"id":405,"firstName":"Rowe","lastName":"Readmire","dateBirth":"2/6/1969","sex":"F"},
{"id":406,"firstName":"Etan","lastName":"Richfield","dateBirth":"1/2/1984","sex":"M"},
{"id":407,"firstName":"Mellisent","lastName":"Elgey","dateBirth":"7/1/1951","sex":"F"},
{"id":408,"firstName":"Vinny","lastName":"Gorden","dateBirth":"5/7/1993","sex":"F"},
{"id":409,"firstName":"Parrnell","lastName":"Mettricke","dateBirth":"1/9/1947","sex":"M"},
{"id":410,"firstName":"Montgomery","lastName":"Philler","dateBirth":"4/7/1952","sex":"M"},
{"id":411,"firstName":"Enriqueta","lastName":"Bolliver","dateBirth":"12/23/1934","sex":"F"},
{"id":412,"firstName":"Riobard","lastName":"Balston","dateBirth":"8/7/1992","sex":"M"},
{"id":413,"firstName":"Dominick","lastName":"Driver","dateBirth":"1/14/1937","sex":"M"},
{"id":414,"firstName":"Kareem","lastName":"Koubek","dateBirth":"3/28/1918","sex":"M"},
{"id":415,"firstName":"Melania","lastName":"Buckwell","dateBirth":"5/10/1908","sex":"F"},
{"id":416,"firstName":"Nate","lastName":"Maton","dateBirth":"3/27/1948","sex":"M"},
{"id":417,"firstName":"Winnie","lastName":"Meechan","dateBirth":"9/22/1925","sex":"M"},
{"id":418,"firstName":"Augie","lastName":"Tschirasche","dateBirth":"12/18/1961","sex":"M"},
{"id":419,"firstName":"Devlen","lastName":"Frawley","dateBirth":"1/20/1924","sex":"M"},
{"id":420,"firstName":"Hugibert","lastName":"Bonifazio","dateBirth":"12/19/1989","sex":"M"},
{"id":421,"firstName":"Arleta","lastName":"Pakes","dateBirth":"12/14/1947","sex":"F"},
{"id":422,"firstName":"Sherilyn","lastName":"Idenden","dateBirth":"3/27/1911","sex":"F"},
{"id":423,"firstName":"Michaela","lastName":"Illsley","dateBirth":"7/20/1969","sex":"F"},
{"id":424,"firstName":"Zed","lastName":"Milius","dateBirth":"2/4/1932","sex":"M"},
{"id":425,"firstName":"Matthieu","lastName":"Dockery","dateBirth":"8/8/1958","sex":"M"},
{"id":426,"firstName":"Doralyn","lastName":"O'Moylane","dateBirth":"6/23/1972","sex":"F"},
{"id":427,"firstName":"Valdemar","lastName":"Duchesne","dateBirth":"2/8/1929","sex":"M"},
{"id":428,"firstName":"Thibaud","lastName":"Stripling","dateBirth":"4/30/1956","sex":"M"},
{"id":429,"firstName":"Coop","lastName":"Huggett","dateBirth":"4/25/1909","sex":"M"},
{"id":430,"firstName":"Ida","lastName":"Zambon","dateBirth":"7/15/1990","sex":"F"},
{"id":431,"firstName":"Marcelle","lastName":"Carabine","dateBirth":"1/21/1961","sex":"F"},
{"id":432,"firstName":"Cassie","lastName":"Flipsen","dateBirth":"2/1/1925","sex":"F"},
{"id":433,"firstName":"Hermann","lastName":"Reisen","dateBirth":"4/17/1913","sex":"M"},
{"id":434,"firstName":"Shamus","lastName":"Biasio","dateBirth":"11/13/1933","sex":"M"},
{"id":435,"firstName":"Packston","lastName":"Drew-Clifton","dateBirth":"9/15/1999","sex":"M"},
{"id":436,"firstName":"Winslow","lastName":"Cuttings","dateBirth":"11/1/1958","sex":"M"},
{"id":437,"firstName":"Gasparo","lastName":"Cartner","dateBirth":"7/16/1983","sex":"M"},
{"id":438,"firstName":"Rivi","lastName":"Naden","dateBirth":"1/17/1933","sex":"F"},
{"id":439,"firstName":"Hallie","lastName":"Mowen","dateBirth":"8/23/1942","sex":"F"},
{"id":440,"firstName":"Cammy","lastName":"Tomek","dateBirth":"8/19/1925","sex":"M"},
{"id":441,"firstName":"Margery","lastName":"Bleiman","dateBirth":"5/21/1936","sex":"F"},
{"id":442,"firstName":"Pansie","lastName":"Pesic","dateBirth":"8/8/1966","sex":"F"},
{"id":443,"firstName":"Dottie","lastName":"Somerbell","dateBirth":"4/26/1905","sex":"F"},
{"id":444,"firstName":"Coriss","lastName":"Itzkovitch","dateBirth":"4/23/1910","sex":"F"},
{"id":445,"firstName":"Sharity","lastName":"Gounin","dateBirth":"8/5/1973","sex":"F"},
{"id":446,"firstName":"Devlen","lastName":"Holleran","dateBirth":"7/30/1962","sex":"M"},
{"id":447,"firstName":"Marissa","lastName":"O'Geaney","dateBirth":"1/5/1966","sex":"F"},
{"id":448,"firstName":"Isahella","lastName":"Piens","dateBirth":"6/29/1907","sex":"F"},
{"id":449,"firstName":"Madelon","lastName":"Marjanovic","dateBirth":"1/14/1986","sex":"F"},
{"id":450,"firstName":"Guss","lastName":"Zecchini","dateBirth":"11/29/1990","sex":"M"},
{"id":451,"firstName":"Krystal","lastName":"Dumbarton","dateBirth":"9/13/1944","sex":"F"},
{"id":452,"firstName":"Nestor","lastName":"Gibbetts","dateBirth":"12/2/1935","sex":"M"},
{"id":453,"firstName":"Nealy","lastName":"Cordier","dateBirth":"6/16/2000","sex":"M"},
{"id":454,"firstName":"Audrey","lastName":"McElroy","dateBirth":"6/11/1996","sex":"F"},
{"id":455,"firstName":"Harrietta","lastName":"Flament","dateBirth":"1/17/1955","sex":"F"},
{"id":456,"firstName":"Bogart","lastName":"Ashe","dateBirth":"9/3/1919","sex":"M"},
{"id":457,"firstName":"Amanda","lastName":"Madgwich","dateBirth":"11/14/1958","sex":"F"},
{"id":458,"firstName":"Vic","lastName":"O Mullen","dateBirth":"1/25/1943","sex":"M"},
{"id":459,"firstName":"Desiree","lastName":"Goodsal","dateBirth":"9/1/2003","sex":"F"},
{"id":460,"firstName":"Keen","lastName":"Fever","dateBirth":"7/7/1922","sex":"M"},
{"id":461,"firstName":"Violetta","lastName":"Culkin","dateBirth":"4/21/1997","sex":"F"},
{"id":462,"firstName":"Mathilda","lastName":"Gatheridge","dateBirth":"5/31/1935","sex":"F"},
{"id":463,"firstName":"Marlie","lastName":"Aveling","dateBirth":"3/3/1926","sex":"F"},
{"id":464,"firstName":"Misty","lastName":"Dinsell","dateBirth":"11/2/2002","sex":"F"},
{"id":465,"firstName":"Xaviera","lastName":"Corcoran","dateBirth":"9/6/1953","sex":"F"},
{"id":466,"firstName":"Bar","lastName":"Jugging","dateBirth":"7/30/1931","sex":"M"},
{"id":467,"firstName":"Hattie","lastName":"Pitchford","dateBirth":"12/21/1957","sex":"F"},
{"id":468,"firstName":"Erskine","lastName":"Calterone","dateBirth":"6/16/1999","sex":"M"},
{"id":469,"firstName":"Georgie","lastName":"Van Baaren","dateBirth":"5/18/1930","sex":"M"},
{"id":470,"firstName":"Daryle","lastName":"Stivani","dateBirth":"1/25/1937","sex":"M"},
{"id":471,"firstName":"Barrie","lastName":"Kingsnode","dateBirth":"5/12/1920","sex":"F"},
{"id":472,"firstName":"Van","lastName":"Matthewes","dateBirth":"11/28/2003","sex":"F"},
{"id":473,"firstName":"Chaunce","lastName":"Hoyte","dateBirth":"1/17/1906","sex":"M"},
{"id":474,"firstName":"Henrik","lastName":"Bolzmann","dateBirth":"8/16/1991","sex":"M"},
{"id":475,"firstName":"Sigfried","lastName":"Guinan","dateBirth":"7/21/1980","sex":"M"},
{"id":476,"firstName":"Jillana","lastName":"Bollum","dateBirth":"7/26/1936","sex":"F"},
{"id":477,"firstName":"Olenka","lastName":"Standingford","dateBirth":"9/5/1976","sex":"F"},
{"id":478,"firstName":"Kory","lastName":"Yegorev","dateBirth":"10/17/1983","sex":"M"},
{"id":479,"firstName":"Eziechiele","lastName":"Gregory","dateBirth":"6/8/1965","sex":"M"},
{"id":480,"firstName":"Garfield","lastName":"Downer","dateBirth":"2/20/1942","sex":"M"},
{"id":481,"firstName":"Iris","lastName":"Warrack","dateBirth":"4/11/2002","sex":"F"},
{"id":482,"firstName":"Atalanta","lastName":"Trumble","dateBirth":"4/2/2003","sex":"F"},
{"id":483,"firstName":"Barbaraanne","lastName":"Shilston","dateBirth":"6/23/1994","sex":"F"},
{"id":484,"firstName":"Obediah","lastName":"Wiffill","dateBirth":"12/13/1918","sex":"M"},
{"id":485,"firstName":"Rorie","lastName":"McFadin","dateBirth":"11/20/1943","sex":"F"},
{"id":486,"firstName":"Channa","lastName":"MacCague","dateBirth":"3/23/1945","sex":"F"},
{"id":487,"firstName":"Gaby","lastName":"Seiler","dateBirth":"12/27/1993","sex":"M"},
{"id":488,"firstName":"Marwin","lastName":"MacNish","dateBirth":"5/8/1977","sex":"M"},
{"id":489,"firstName":"Shamus","lastName":"Begley","dateBirth":"2/12/1993","sex":"M"},
{"id":490,"firstName":"Joleen","lastName":"Dowle","dateBirth":"6/25/1983","sex":"F"},
{"id":491,"firstName":"Marlin","lastName":"Priddle","dateBirth":"4/18/1939","sex":"M"},
{"id":492,"firstName":"Thacher","lastName":"Purbrick","dateBirth":"7/21/1934","sex":"M"},
{"id":493,"firstName":"Fred","lastName":"Coppenhall","dateBirth":"11/16/1954","sex":"M"},
{"id":494,"firstName":"Gaile","lastName":"Ravenshaw","dateBirth":"6/4/1973","sex":"M"},
{"id":495,"firstName":"Rockwell","lastName":"Gaspar","dateBirth":"9/11/1953","sex":"M"},
{"id":496,"firstName":"Janos","lastName":"Bellson","dateBirth":"7/9/1995","sex":"M"},
{"id":497,"firstName":"Rora","lastName":"Bourrel","dateBirth":"2/18/1986","sex":"F"},
{"id":498,"firstName":"Maris","lastName":"Proven","dateBirth":"9/4/1969","sex":"F"},
{"id":499,"firstName":"Margret","lastName":"Hearsum","dateBirth":"11/21/1927","sex":"F"},
{"id":500,"firstName":"Harrison","lastName":"Balaisot","dateBirth":"5/27/1972","sex":"M"},
{"id":501,"firstName":"Norris","lastName":"Cotilard","dateBirth":"4/11/1940","sex":"M"},
{"id":502,"firstName":"Lilah","lastName":"Hartup","dateBirth":"2/7/1913","sex":"F"},
{"id":503,"firstName":"Rose","lastName":"Imort","dateBirth":"3/25/1952","sex":"F"},
{"id":504,"firstName":"Stanislaus","lastName":"Foxley","dateBirth":"1/8/1920","sex":"M"},
{"id":505,"firstName":"Elwood","lastName":"Lyokhin","dateBirth":"12/7/1946","sex":"M"},
{"id":506,"firstName":"Archer","lastName":"Placstone","dateBirth":"11/23/1990","sex":"M"},
{"id":507,"firstName":"Hetti","lastName":"Hinckley","dateBirth":"9/21/2004","sex":"F"},
{"id":508,"firstName":"Gustavus","lastName":"Servant","dateBirth":"7/12/1993","sex":"M"},
{"id":509,"firstName":"Lanie","lastName":"Blenkin","dateBirth":"2/16/1958","sex":"M"},
{"id":510,"firstName":"Annadiana","lastName":"Bernardet","dateBirth":"3/19/1965","sex":"F"},
{"id":511,"firstName":"Kelsi","lastName":"Chipperfield","dateBirth":"2/10/2005","sex":"F"},
{"id":512,"firstName":"Maje","lastName":"Joskowitz","dateBirth":"3/1/1987","sex":"M"},
{"id":513,"firstName":"Ernst","lastName":"Huddlestone","dateBirth":"5/10/1962","sex":"M"},
{"id":514,"firstName":"Bianca","lastName":"Collelton","dateBirth":"8/20/1988","sex":"F"},
{"id":515,"firstName":"Rheba","lastName":"Callen","dateBirth":"7/1/1939","sex":"F"},
{"id":516,"firstName":"Luis","lastName":"Sammars","dateBirth":"10/29/1925","sex":"M"},
{"id":517,"firstName":"Shaina","lastName":"Deegin","dateBirth":"9/21/1931","sex":"F"},
{"id":518,"firstName":"Carmelita","lastName":"Skilbeck","dateBirth":"1/15/1943","sex":"F"},
{"id":519,"firstName":"Fayre","lastName":"Spray","dateBirth":"1/11/1984","sex":"F"},
{"id":520,"firstName":"Aeriela","lastName":"England","dateBirth":"7/18/1966","sex":"F"},
{"id":521,"firstName":"Cindy","lastName":"Dumbrill","dateBirth":"11/5/1988","sex":"F"},
{"id":522,"firstName":"Karolina","lastName":"Matteini","dateBirth":"2/16/1986","sex":"F"},
{"id":523,"firstName":"Samaria","lastName":"Gyorgy","dateBirth":"10/4/1989","sex":"F"},
{"id":524,"firstName":"Britt","lastName":"Denzilow","dateBirth":"10/4/1959","sex":"M"},
{"id":525,"firstName":"Niccolo","lastName":"Bullas","dateBirth":"6/25/1980","sex":"M"},
{"id":526,"firstName":"Ilaire","lastName":"Scanes","dateBirth":"8/29/1976","sex":"M"},
{"id":527,"firstName":"Cozmo","lastName":"Skeldon","dateBirth":"3/7/1932","sex":"M"},
{"id":528,"firstName":"Nathanial","lastName":"June","dateBirth":"4/11/1949","sex":"M"},
{"id":529,"firstName":"Hewet","lastName":"Keston","dateBirth":"9/7/1993","sex":"M"},
{"id":530,"firstName":"Donetta","lastName":"Keppe","dateBirth":"3/16/1963","sex":"F"},
{"id":531,"firstName":"Killie","lastName":"Karlsen","dateBirth":"10/26/1933","sex":"M"},
{"id":532,"firstName":"Fin","lastName":"Carlino","dateBirth":"8/27/1913","sex":"M"},
{"id":533,"firstName":"Vince","lastName":"Dolby","dateBirth":"1/27/1930","sex":"M"},
{"id":534,"firstName":"Rabi","lastName":"Kissock","dateBirth":"10/13/1921","sex":"M"},
{"id":535,"firstName":"Amberly","lastName":"Worsnop","dateBirth":"3/30/2002","sex":"F"},
{"id":536,"firstName":"Erin","lastName":"Clears","dateBirth":"9/2/1967","sex":"M"},
{"id":537,"firstName":"Lane","lastName":"Toderini","dateBirth":"4/24/1905","sex":"F"},
{"id":538,"firstName":"Innis","lastName":"Mauchlen","dateBirth":"6/13/1931","sex":"M"},
{"id":539,"firstName":"Debra","lastName":"Astall","dateBirth":"12/30/1924","sex":"F"},
{"id":540,"firstName":"Rutherford","lastName":"Fouldes","dateBirth":"9/6/1986","sex":"M"},
{"id":541,"firstName":"Rod","lastName":"Teaser","dateBirth":"10/28/1952","sex":"M"},
{"id":542,"firstName":"Amie","lastName":"Byas","dateBirth":"3/16/1927","sex":"F"},
{"id":543,"firstName":"Fabio","lastName":"Kubicki","dateBirth":"10/12/1988","sex":"M"},
{"id":544,"firstName":"Glenn","lastName":"Buttery","dateBirth":"12/4/1942","sex":"M"},
{"id":545,"firstName":"Polly","lastName":"Olufsen","dateBirth":"4/15/1992","sex":"F"},
{"id":546,"firstName":"Amory","lastName":"Joskowitz","dateBirth":"5/31/1979","sex":"M"},
{"id":547,"firstName":"Obie","lastName":"Duckham","dateBirth":"11/21/1942","sex":"M"},
{"id":548,"firstName":"Murielle","lastName":"Beynon","dateBirth":"9/13/1940","sex":"F"},
{"id":549,"firstName":"Derrick","lastName":"Whitebread","dateBirth":"6/21/1983","sex":"M"},
{"id":550,"firstName":"Callida","lastName":"Sasser","dateBirth":"3/30/2001","sex":"F"},
{"id":551,"firstName":"Tonya","lastName":"Pymm","dateBirth":"7/17/1914","sex":"F"},
{"id":552,"firstName":"Walliw","lastName":"Litherborough","dateBirth":"11/27/1988","sex":"F"},
{"id":553,"firstName":"Juliann","lastName":"Doulton","dateBirth":"9/5/1911","sex":"F"},
{"id":554,"firstName":"Shurwood","lastName":"Pauletto","dateBirth":"12/1/1942","sex":"M"},
{"id":555,"firstName":"Nichol","lastName":"Lindmark","dateBirth":"3/18/1953","sex":"F"},
{"id":556,"firstName":"Bale","lastName":"Connikie","dateBirth":"10/30/1908","sex":"M"},
{"id":557,"firstName":"Kizzie","lastName":"Bilby","dateBirth":"1/6/1941","sex":"F"},
{"id":558,"firstName":"Wyatt","lastName":"Wyness","dateBirth":"12/21/1996","sex":"M"},
{"id":559,"firstName":"Geoffry","lastName":"Pock","dateBirth":"11/19/1995","sex":"M"},
{"id":560,"firstName":"Mahala","lastName":"Murname","dateBirth":"6/27/1981","sex":"F"},
{"id":561,"firstName":"Hamish","lastName":"Hanfrey","dateBirth":"3/31/1929","sex":"M"},
{"id":562,"firstName":"Jacky","lastName":"Cossem","dateBirth":"10/8/1909","sex":"F"},
{"id":563,"firstName":"Tara","lastName":"Cowup","dateBirth":"11/21/1957","sex":"F"},
{"id":564,"firstName":"Aurel","lastName":"Peasnone","dateBirth":"9/9/1961","sex":"F"},
{"id":565,"firstName":"Mano","lastName":"Bees","dateBirth":"12/17/1913","sex":"M"},
{"id":566,"firstName":"Vail","lastName":"Laugheran","dateBirth":"6/16/1942","sex":"M"},
{"id":567,"firstName":"Tuesday","lastName":"Jillions","dateBirth":"4/16/1911","sex":"F"},
{"id":568,"firstName":"Tori","lastName":"Vedekhin","dateBirth":"4/26/1968","sex":"F"},
{"id":569,"firstName":"Kermie","lastName":"Foulsham","dateBirth":"7/1/1908","sex":"M"},
{"id":570,"firstName":"Wynn","lastName":"Attwell","dateBirth":"3/12/1910","sex":"F"},
{"id":571,"firstName":"Danya","lastName":"Carl","dateBirth":"11/27/1952","sex":"M"},
{"id":572,"firstName":"Gavra","lastName":"Kulis","dateBirth":"6/11/1945","sex":"F"},
{"id":573,"firstName":"Cyrillus","lastName":"Oates","dateBirth":"4/2/1946","sex":"M"},
{"id":574,"firstName":"Clayson","lastName":"Bentzen","dateBirth":"5/5/1913","sex":"M"},
{"id":575,"firstName":"Hollyanne","lastName":"McGavin","dateBirth":"1/21/1994","sex":"F"},
{"id":576,"firstName":"Heinrik","lastName":"Savatier","dateBirth":"7/8/1957","sex":"M"},
{"id":577,"firstName":"Myrta","lastName":"Sendley","dateBirth":"1/25/2003","sex":"F"},
{"id":578,"firstName":"Ingaberg","lastName":"McDonogh","dateBirth":"5/16/1913","sex":"F"},
{"id":579,"firstName":"Marielle","lastName":"Gianinotti","dateBirth":"4/3/1984","sex":"F"},
{"id":580,"firstName":"Torrance","lastName":"Ors","dateBirth":"10/5/1968","sex":"M"},
{"id":581,"firstName":"Cordi","lastName":"Layton","dateBirth":"4/28/1928","sex":"F"},
{"id":582,"firstName":"Stesha","lastName":"Ducroe","dateBirth":"4/26/1954","sex":"F"},
{"id":583,"firstName":"Teddie","lastName":"Cinnamond","dateBirth":"4/2/1958","sex":"M"},
{"id":584,"firstName":"Devin","lastName":"Leppard","dateBirth":"6/20/1942","sex":"M"},
{"id":585,"firstName":"Jasen","lastName":"Godridge","dateBirth":"1/12/1942","sex":"M"},
{"id":586,"firstName":"Mata","lastName":"Sentinella","dateBirth":"12/16/1997","sex":"M"},
{"id":587,"firstName":"Gale","lastName":"Mustill","dateBirth":"9/25/1913","sex":"F"},
{"id":588,"firstName":"Demetri","lastName":"Rushby","dateBirth":"2/9/1980","sex":"M"},
{"id":589,"firstName":"Raviv","lastName":"Laugheran","dateBirth":"7/2/1924","sex":"M"},
{"id":590,"firstName":"Sergeant","lastName":"Footitt","dateBirth":"6/4/1934","sex":"M"},
{"id":591,"firstName":"Dione","lastName":"Ranner","dateBirth":"6/10/2004","sex":"F"},
{"id":592,"firstName":"Hertha","lastName":"Ciraldo","dateBirth":"4/20/1979","sex":"F"},
{"id":593,"firstName":"Mable","lastName":"Lippiello","dateBirth":"12/25/1940","sex":"F"},
{"id":594,"firstName":"Isidoro","lastName":"Izkovitch","dateBirth":"7/22/1942","sex":"M"},
{"id":595,"firstName":"Salem","lastName":"Chaim","dateBirth":"1/14/1971","sex":"M"},
{"id":596,"firstName":"Vaughn","lastName":"Ivins","dateBirth":"5/19/1975","sex":"M"},
{"id":597,"firstName":"Clementina","lastName":"Jorden","dateBirth":"11/20/1929","sex":"F"},
{"id":598,"firstName":"Patty","lastName":"De Mitris","dateBirth":"8/3/1956","sex":"M"},
{"id":599,"firstName":"Leoline","lastName":"Cheers","dateBirth":"7/28/1967","sex":"F"},
{"id":600,"firstName":"Earl","lastName":"Rubinov","dateBirth":"9/9/1985","sex":"M"},
{"id":601,"firstName":"Fredericka","lastName":"Kharchinski","dateBirth":"11/18/1908","sex":"F"},
{"id":602,"firstName":"Christabella","lastName":"Puddan","dateBirth":"6/29/1978","sex":"F"},
{"id":603,"firstName":"Bel","lastName":"Feuell","dateBirth":"8/2/1958","sex":"F"},
{"id":604,"firstName":"Janeczka","lastName":"Kadwallider","dateBirth":"11/30/1932","sex":"F"},
{"id":605,"firstName":"Smitty","lastName":"Benkin","dateBirth":"12/7/1938","sex":"M"},
{"id":606,"firstName":"Cheston","lastName":"Couling","dateBirth":"9/15/1980","sex":"M"},
{"id":607,"firstName":"Elnora","lastName":"Gioan","dateBirth":"9/9/1932","sex":"F"},
{"id":608,"firstName":"Hall","lastName":"Grise","dateBirth":"11/21/1917","sex":"M"},
{"id":609,"firstName":"Doralynne","lastName":"Moulding","dateBirth":"10/11/1995","sex":"F"},
{"id":610,"firstName":"Bette-ann","lastName":"Tettley","dateBirth":"5/7/1947","sex":"F"},
{"id":611,"firstName":"Orrin","lastName":"Durdle","dateBirth":"3/14/1943","sex":"M"},
{"id":612,"firstName":"Zared","lastName":"Patriskson","dateBirth":"1/17/1986","sex":"M"},
{"id":613,"firstName":"Jessi","lastName":"Leve","dateBirth":"3/7/1971","sex":"F"},
{"id":614,"firstName":"Irving","lastName":"Birtwisle","dateBirth":"7/13/1933","sex":"M"},
{"id":615,"firstName":"Kip","lastName":"Olivella","dateBirth":"10/2/1922","sex":"M"},
{"id":616,"firstName":"Mattias","lastName":"Balogh","dateBirth":"5/18/1956","sex":"M"},
{"id":617,"firstName":"Rosamond","lastName":"Spellacy","dateBirth":"11/14/1974","sex":"F"},
{"id":618,"firstName":"Howey","lastName":"Overton","dateBirth":"5/12/1931","sex":"M"},
{"id":619,"firstName":"Benson","lastName":"Lis","dateBirth":"4/23/1962","sex":"M"},
{"id":620,"firstName":"Heida","lastName":"De Lorenzo","dateBirth":"5/21/1999","sex":"F"},
{"id":621,"firstName":"Linnell","lastName":"Olek","dateBirth":"11/8/1995","sex":"F"},
{"id":622,"firstName":"Alvin","lastName":"Meffen","dateBirth":"6/24/1968","sex":"M"},
{"id":623,"firstName":"Francoise","lastName":"Simonassi","dateBirth":"7/20/1941","sex":"F"},
{"id":624,"firstName":"Marya","lastName":"Tribble","dateBirth":"9/8/1975","sex":"F"},
{"id":625,"firstName":"Monique","lastName":"Gairdner","dateBirth":"3/11/1980","sex":"F"},
{"id":626,"firstName":"Melinda","lastName":"Shepland","dateBirth":"6/19/1911","sex":"F"},
{"id":627,"firstName":"Drucie","lastName":"Twelvetree","dateBirth":"5/27/1909","sex":"F"},
{"id":628,"firstName":"Cinderella","lastName":"Glassup","dateBirth":"12/6/1930","sex":"F"},
{"id":629,"firstName":"Denna","lastName":"Mullard","dateBirth":"5/7/1949","sex":"F"},
{"id":630,"firstName":"Mariele","lastName":"Kinnaird","dateBirth":"7/17/1998","sex":"F"},
{"id":631,"firstName":"Sigvard","lastName":"Richt","dateBirth":"3/21/1987","sex":"M"},
{"id":632,"firstName":"Cacilie","lastName":"Grayham","dateBirth":"10/11/1996","sex":"F"},
{"id":633,"firstName":"Hadlee","lastName":"Seckom","dateBirth":"10/25/2003","sex":"M"},
{"id":634,"firstName":"Derry","lastName":"Gilmour","dateBirth":"2/18/1996","sex":"M"},
{"id":635,"firstName":"Terry","lastName":"Lamort","dateBirth":"9/14/1984","sex":"M"},
{"id":636,"firstName":"Pearline","lastName":"Lamputt","dateBirth":"10/15/1933","sex":"F"},
{"id":637,"firstName":"Erina","lastName":"Chestnut","dateBirth":"3/27/1951","sex":"F"},
{"id":638,"firstName":"Mallory","lastName":"Cleeve","dateBirth":"3/23/1973","sex":"F"},
{"id":639,"firstName":"Tilda","lastName":"Nilles","dateBirth":"5/1/1988","sex":"F"},
{"id":640,"firstName":"Beckie","lastName":"Ambler","dateBirth":"12/27/1950","sex":"F"},
{"id":641,"firstName":"Jarib","lastName":"Scruton","dateBirth":"11/22/1965","sex":"M"},
{"id":642,"firstName":"Jordan","lastName":"Kahan","dateBirth":"2/19/1920","sex":"F"},
{"id":643,"firstName":"Herrick","lastName":"Coysh","dateBirth":"4/6/2005","sex":"M"},
{"id":644,"firstName":"Tod","lastName":"Ison","dateBirth":"4/24/1988","sex":"M"},
{"id":645,"firstName":"Nikola","lastName":"Keatley","dateBirth":"3/26/1962","sex":"M"},
{"id":646,"firstName":"Gracia","lastName":"Heustice","dateBirth":"11/18/1988","sex":"F"},
{"id":647,"firstName":"Paige","lastName":"Costell","dateBirth":"7/13/1974","sex":"M"},
{"id":648,"firstName":"Curry","lastName":"Goodwin","dateBirth":"5/10/1909","sex":"M"},
{"id":649,"firstName":"Nathalie","lastName":"Mumbeson","dateBirth":"3/31/1919","sex":"F"},
{"id":650,"firstName":"Lyndsay","lastName":"Lujan","dateBirth":"2/27/1972","sex":"F"},
{"id":651,"firstName":"Peggy","lastName":"Dunster","dateBirth":"11/26/1907","sex":"F"},
{"id":652,"firstName":"Prudence","lastName":"Brigstock","dateBirth":"10/8/1954","sex":"F"},
{"id":653,"firstName":"Wallache","lastName":"O' Scallan","dateBirth":"4/30/1965","sex":"M"},
{"id":654,"firstName":"Avrit","lastName":"McQuaide","dateBirth":"12/20/1938","sex":"F"},
{"id":655,"firstName":"Zedekiah","lastName":"Lower","dateBirth":"2/5/1924","sex":"M"},
{"id":656,"firstName":"Rickie","lastName":"Frantz","dateBirth":"8/11/1935","sex":"M"},
{"id":657,"firstName":"Lotti","lastName":"Inchboard","dateBirth":"3/15/1957","sex":"F"},
{"id":658,"firstName":"Selia","lastName":"Paschke","dateBirth":"11/5/1954","sex":"F"},
{"id":659,"firstName":"Karlyn","lastName":"Cavendish","dateBirth":"12/9/1964","sex":"F"},
{"id":660,"firstName":"Georg","lastName":"Kumar","dateBirth":"11/27/1952","sex":"M"},
{"id":661,"firstName":"Willy","lastName":"Wattinham","dateBirth":"6/29/1984","sex":"M"},
{"id":662,"firstName":"Karly","lastName":"Chiplin","dateBirth":"11/11/1953","sex":"F"},
{"id":663,"firstName":"Vincent","lastName":"McCullouch","dateBirth":"5/28/1912","sex":"M"},
{"id":664,"firstName":"Betti","lastName":"Lowdyane","dateBirth":"7/30/1947","sex":"F"},
{"id":665,"firstName":"Harley","lastName":"Giacometti","dateBirth":"5/28/1953","sex":"F"},
{"id":666,"firstName":"Aaren","lastName":"Allchorne","dateBirth":"3/7/1921","sex":"F"},
{"id":667,"firstName":"Juieta","lastName":"O'Griffin","dateBirth":"2/14/1926","sex":"F"},
{"id":668,"firstName":"Rees","lastName":"Bever","dateBirth":"7/28/1997","sex":"M"},
{"id":669,"firstName":"Ewan","lastName":"Wildt","dateBirth":"6/7/1996","sex":"M"},
{"id":670,"firstName":"Reeta","lastName":"Engledow","dateBirth":"5/10/1940","sex":"F"},
{"id":671,"firstName":"Brucie","lastName":"Rembrandt","dateBirth":"10/1/1926","sex":"M"},
{"id":672,"firstName":"Olimpia","lastName":"Bezley","dateBirth":"9/16/1938","sex":"F"},
{"id":673,"firstName":"Krishna","lastName":"Stannard","dateBirth":"8/16/1933","sex":"M"},
{"id":674,"firstName":"Ardelle","lastName":"Davey","dateBirth":"4/4/1929","sex":"F"},
{"id":675,"firstName":"Hannis","lastName":"Quinney","dateBirth":"6/22/1971","sex":"F"},
{"id":676,"firstName":"Ola","lastName":"Jobling","dateBirth":"10/14/1983","sex":"F"},
{"id":677,"firstName":"Collete","lastName":"Tomanek","dateBirth":"10/31/1906","sex":"F"},
{"id":678,"firstName":"Kirk","lastName":"Dwane","dateBirth":"4/26/1960","sex":"M"},
{"id":679,"firstName":"Nikolaus","lastName":"Pamment","dateBirth":"5/15/1989","sex":"M"},
{"id":680,"firstName":"Lanie","lastName":"Dearsley","dateBirth":"1/11/1936","sex":"M"},
{"id":681,"firstName":"Hewitt","lastName":"Quest","dateBirth":"4/20/1919","sex":"M"},
{"id":682,"firstName":"Barron","lastName":"Posten","dateBirth":"8/25/1991","sex":"M"},
{"id":683,"firstName":"Nicko","lastName":"Hacun","dateBirth":"5/23/1987","sex":"M"},
{"id":684,"firstName":"Heddie","lastName":"Cancelier","dateBirth":"2/16/1962","sex":"F"},
{"id":685,"firstName":"Horatius","lastName":"Kops","dateBirth":"4/13/1922","sex":"M"},
{"id":686,"firstName":"Ardella","lastName":"Stokell","dateBirth":"12/9/1981","sex":"F"},
{"id":687,"firstName":"Karena","lastName":"Youel","dateBirth":"12/7/1987","sex":"F"},
{"id":688,"firstName":"Trumaine","lastName":"Maffetti","dateBirth":"1/31/1944","sex":"M"},
{"id":689,"firstName":"Troy","lastName":"Moatt","dateBirth":"1/5/1987","sex":"M"},
{"id":690,"firstName":"Layton","lastName":"Brompton","dateBirth":"6/7/1976","sex":"M"},
{"id":691,"firstName":"Johnnie","lastName":"O'Monahan","dateBirth":"2/2/1925","sex":"M"},
{"id":692,"firstName":"Minnnie","lastName":"McKyrrelly","dateBirth":"7/13/1917","sex":"F"},
{"id":693,"firstName":"Brit","lastName":"Rowth","dateBirth":"4/12/1923","sex":"M"},
{"id":694,"firstName":"Carline","lastName":"Ioan","dateBirth":"4/29/1913","sex":"F"},
{"id":695,"firstName":"Kristoforo","lastName":"Stuchberry","dateBirth":"6/22/1988","sex":"M"},
{"id":696,"firstName":"Aurthur","lastName":"Kerfut","dateBirth":"1/4/2001","sex":"M"},
{"id":697,"firstName":"Westbrook","lastName":"Szimoni","dateBirth":"9/10/1984","sex":"M"},
{"id":698,"firstName":"Miguela","lastName":"Kender","dateBirth":"11/3/1955","sex":"F"},
{"id":699,"firstName":"Fedora","lastName":"Ringham","dateBirth":"7/5/1934","sex":"F"},
{"id":700,"firstName":"Karlie","lastName":"Bauduccio","dateBirth":"12/27/1960","sex":"F"},
{"id":701,"firstName":"Clair","lastName":"Conry","dateBirth":"2/3/1938","sex":"F"},
{"id":702,"firstName":"Bradford","lastName":"Gallahar","dateBirth":"6/15/1969","sex":"M"},
{"id":703,"firstName":"Jeremie","lastName":"O'Deoran","dateBirth":"10/12/1967","sex":"M"},
{"id":704,"firstName":"Amery","lastName":"Savoury","dateBirth":"11/8/1913","sex":"M"},
{"id":705,"firstName":"Belia","lastName":"Featherstonhaugh","dateBirth":"9/9/1918","sex":"F"},
{"id":706,"firstName":"Briant","lastName":"Asson","dateBirth":"7/1/1907","sex":"M"},
{"id":707,"firstName":"Thomasa","lastName":"Hardinge","dateBirth":"3/1/1962","sex":"F"},
{"id":708,"firstName":"Giustino","lastName":"Pettingall","dateBirth":"12/15/1980","sex":"M"},
{"id":709,"firstName":"Hugh","lastName":"Benley","dateBirth":"7/3/1940","sex":"M"},
{"id":710,"firstName":"Care","lastName":"Haibel","dateBirth":"3/23/1959","sex":"M"},
{"id":711,"firstName":"Parrnell","lastName":"Reihill","dateBirth":"9/14/1946","sex":"M"},
{"id":712,"firstName":"Rutger","lastName":"Fourman","dateBirth":"2/3/1947","sex":"M"},
{"id":713,"firstName":"Cathee","lastName":"Di Angelo","dateBirth":"9/30/1998","sex":"F"},
{"id":714,"firstName":"Lanie","lastName":"Barrowcliff","dateBirth":"7/10/1949","sex":"F"},
{"id":715,"firstName":"Samantha","lastName":"Pierro","dateBirth":"6/27/1979","sex":"F"},
{"id":716,"firstName":"Pepillo","lastName":"Quogan","dateBirth":"2/4/1918","sex":"M"},
{"id":717,"firstName":"Frederique","lastName":"Swendell","dateBirth":"12/19/1962","sex":"F"},
{"id":718,"firstName":"Heddi","lastName":"Opy","dateBirth":"8/18/1948","sex":"F"},
{"id":719,"firstName":"Chrisy","lastName":"Lorenzetto","dateBirth":"4/2/1918","sex":"M"},
{"id":720,"firstName":"Starla","lastName":"Gathercoal","dateBirth":"6/27/1986","sex":"F"},
{"id":721,"firstName":"Emlynn","lastName":"Vassall","dateBirth":"7/1/1999","sex":"F"},
{"id":722,"firstName":"Reed","lastName":"Ledward","dateBirth":"7/14/2000","sex":"M"},
{"id":723,"firstName":"Duffie","lastName":"Pegram","dateBirth":"3/30/1980","sex":"M"},
{"id":724,"firstName":"Moyna","lastName":"Liversley","dateBirth":"12/1/1954","sex":"F"},
{"id":725,"firstName":"Herve","lastName":"Catterell","dateBirth":"11/29/1982","sex":"M"},
{"id":726,"firstName":"Moira","lastName":"Rhoades","dateBirth":"10/22/2003","sex":"F"},
{"id":727,"firstName":"Lanie","lastName":"Whiteway","dateBirth":"10/16/1994","sex":"F"},
{"id":728,"firstName":"Martyn","lastName":"Rampage","dateBirth":"10/12/1990","sex":"M"},
{"id":729,"firstName":"Marshal","lastName":"Sedgemond","dateBirth":"1/16/1969","sex":"M"},
{"id":730,"firstName":"Angelique","lastName":"Piccard","dateBirth":"10/13/1938","sex":"F"},
{"id":731,"firstName":"Carmelina","lastName":"Gee","dateBirth":"2/16/1925","sex":"F"},
{"id":732,"firstName":"Corissa","lastName":"Cordobes","dateBirth":"12/3/1978","sex":"F"},
{"id":733,"firstName":"Brant","lastName":"Maus","dateBirth":"1/15/1969","sex":"M"},
{"id":734,"firstName":"Lacy","lastName":"Volett","dateBirth":"2/10/1975","sex":"F"},
{"id":735,"firstName":"Tim","lastName":"O'Gorman","dateBirth":"8/4/1932","sex":"F"},
{"id":736,"firstName":"Mart","lastName":"Allom","dateBirth":"12/31/1919","sex":"M"},
{"id":737,"firstName":"Mic","lastName":"Rennles","dateBirth":"6/18/1910","sex":"M"},
{"id":738,"firstName":"Lucais","lastName":"O'dell","dateBirth":"1/5/1958","sex":"M"},
{"id":739,"firstName":"Valencia","lastName":"Kurtis","dateBirth":"6/2/1927","sex":"F"},
{"id":740,"firstName":"Horatius","lastName":"Lunam","dateBirth":"9/27/1992","sex":"M"},
{"id":741,"firstName":"Gwendolin","lastName":"MacAllen","dateBirth":"7/28/1920","sex":"F"},
{"id":742,"firstName":"Arnold","lastName":"Boykett","dateBirth":"2/19/1990","sex":"M"},
{"id":743,"firstName":"Rycca","lastName":"Goligly","dateBirth":"12/22/1920","sex":"F"},
{"id":744,"firstName":"Frederique","lastName":"Higbin","dateBirth":"10/8/1926","sex":"F"},
{"id":745,"firstName":"Stesha","lastName":"Twiggins","dateBirth":"2/12/1981","sex":"F"},
{"id":746,"firstName":"Albina","lastName":"O'Brollachain","dateBirth":"2/27/1969","sex":"F"},
{"id":747,"firstName":"Robinet","lastName":"Beahan","dateBirth":"5/3/1907","sex":"M"},
{"id":748,"firstName":"Pete","lastName":"Ambrose","dateBirth":"1/8/1923","sex":"M"},
{"id":749,"firstName":"Carlynn","lastName":"Prantoni","dateBirth":"9/25/1999","sex":"F"},
{"id":750,"firstName":"Lena","lastName":"Benninger","dateBirth":"7/20/1978","sex":"F"},
{"id":751,"firstName":"Sonny","lastName":"Upton","dateBirth":"1/28/1968","sex":"M"},
{"id":752,"firstName":"Chen","lastName":"Chamney","dateBirth":"5/25/2004","sex":"M"},
{"id":753,"firstName":"Adams","lastName":"Meininger","dateBirth":"3/5/1992","sex":"M"},
{"id":754,"firstName":"Wenonah","lastName":"Gittens","dateBirth":"7/14/1912","sex":"F"},
{"id":755,"firstName":"Ardelia","lastName":"Laidel","dateBirth":"8/28/1938","sex":"F"},
{"id":756,"firstName":"Willdon","lastName":"Sukbhans","dateBirth":"3/15/1968","sex":"M"},
{"id":757,"firstName":"Glenna","lastName":"Leggate","dateBirth":"5/27/1956","sex":"F"},
{"id":758,"firstName":"Lorianna","lastName":"Ishchenko","dateBirth":"12/16/1980","sex":"F"},
{"id":759,"firstName":"Gert","lastName":"Browning","dateBirth":"6/8/1954","sex":"F"},
{"id":760,"firstName":"Raleigh","lastName":"Towey","dateBirth":"8/1/1993","sex":"M"},
{"id":761,"firstName":"Marybeth","lastName":"Iremonger","dateBirth":"1/3/1939","sex":"F"},
{"id":762,"firstName":"Aarika","lastName":"Bang","dateBirth":"7/5/1921","sex":"F"},
{"id":763,"firstName":"Calypso","lastName":"Dawidowsky","dateBirth":"12/18/1908","sex":"F"},
{"id":764,"firstName":"Rolph","lastName":"Escreet","dateBirth":"10/1/1996","sex":"M"},
{"id":765,"firstName":"Marie-ann","lastName":"Karczinski","dateBirth":"8/8/1995","sex":"F"},
{"id":766,"firstName":"Hannah","lastName":"Kares","dateBirth":"2/10/1990","sex":"F"},
{"id":767,"firstName":"Ginnifer","lastName":"Pudding","dateBirth":"11/8/1926","sex":"F"},
{"id":768,"firstName":"Leonardo","lastName":"Puckrin","dateBirth":"2/4/1996","sex":"M"},
{"id":769,"firstName":"Federico","lastName":"de Leon","dateBirth":"2/20/1912","sex":"M"},
{"id":770,"firstName":"Glynnis","lastName":"Monkton","dateBirth":"5/25/1962","sex":"F"},
{"id":771,"firstName":"Olympie","lastName":"Noades","dateBirth":"6/3/1933","sex":"F"},
{"id":772,"firstName":"Elvis","lastName":"Swindley","dateBirth":"8/14/1969","sex":"M"},
{"id":773,"firstName":"Cyndie","lastName":"Phillput","dateBirth":"9/30/1977","sex":"F"},
{"id":774,"firstName":"Hedy","lastName":"Packington","dateBirth":"8/15/1966","sex":"F"},
{"id":775,"firstName":"Franky","lastName":"Northall","dateBirth":"9/18/1908","sex":"M"},
{"id":776,"firstName":"Idalina","lastName":"Charke","dateBirth":"3/16/1929","sex":"F"},
{"id":777,"firstName":"Tiffani","lastName":"Rickasse","dateBirth":"10/10/1919","sex":"F"},
{"id":778,"firstName":"Kimmi","lastName":"Ough","dateBirth":"9/24/1961","sex":"F"},
{"id":779,"firstName":"Carol-jean","lastName":"Greenfield","dateBirth":"5/24/1980","sex":"F"},
{"id":780,"firstName":"Jere","lastName":"Stimson","dateBirth":"8/5/1920","sex":"M"},
{"id":781,"firstName":"Giorgio","lastName":"Moakson","dateBirth":"6/12/1939","sex":"M"},
{"id":782,"firstName":"Denise","lastName":"Barrow","dateBirth":"9/12/1968","sex":"F"},
{"id":783,"firstName":"Lezlie","lastName":"Milburne","dateBirth":"2/20/1930","sex":"F"},
{"id":784,"firstName":"Odella","lastName":"Gilchriest","dateBirth":"5/31/1922","sex":"F"},
{"id":785,"firstName":"Tabbie","lastName":"Asken","dateBirth":"9/25/2005","sex":"M"},
{"id":786,"firstName":"Auberta","lastName":"Littlewood","dateBirth":"12/24/1907","sex":"F"},
{"id":787,"firstName":"Tonnie","lastName":"Lorkins","dateBirth":"10/6/1959","sex":"M"},
{"id":788,"firstName":"Vinny","lastName":"Oliphard","dateBirth":"12/23/1951","sex":"F"},
{"id":789,"firstName":"Jordon","lastName":"O'Currigan","dateBirth":"5/12/1910","sex":"M"},
{"id":790,"firstName":"Fonzie","lastName":"Pereira","dateBirth":"9/19/1909","sex":"M"},
{"id":791,"firstName":"Nerta","lastName":"Deniset","dateBirth":"10/1/1980","sex":"F"},
{"id":792,"firstName":"Terra","lastName":"Blanpein","dateBirth":"1/3/1921","sex":"F"},
{"id":793,"firstName":"Winni","lastName":"Ettritch","dateBirth":"11/20/1938","sex":"F"},
{"id":794,"firstName":"Lyndy","lastName":"Musselwhite","dateBirth":"12/5/1965","sex":"F"},
{"id":795,"firstName":"Stevana","lastName":"Dionisio","dateBirth":"10/20/1931","sex":"F"},
{"id":796,"firstName":"Regan","lastName":"Eiler","dateBirth":"3/15/1933","sex":"M"},
{"id":797,"firstName":"Taylor","lastName":"Kinnerley","dateBirth":"4/19/1959","sex":"M"},
{"id":798,"firstName":"Jessalin","lastName":"Suscens","dateBirth":"1/16/1961","sex":"F"},
{"id":799,"firstName":"Marline","lastName":"Regnard","dateBirth":"3/8/1910","sex":"F"},
{"id":800,"firstName":"Innis","lastName":"Shimwell","dateBirth":"10/15/1987","sex":"M"},
{"id":801,"firstName":"Holt","lastName":"Savil","dateBirth":"2/6/1925","sex":"M"},
{"id":802,"firstName":"Winne","lastName":"Grazier","dateBirth":"5/13/1916","sex":"F"},
{"id":803,"firstName":"Rivi","lastName":"Goseling","dateBirth":"9/12/1908","sex":"F"},
{"id":804,"firstName":"Marco","lastName":"Loxton","dateBirth":"3/18/2001","sex":"M"},
{"id":805,"firstName":"Dawn","lastName":"Bennell","dateBirth":"1/3/1963","sex":"F"},
{"id":806,"firstName":"Frazer","lastName":"Chilcotte","dateBirth":"8/5/1959","sex":"M"},
{"id":807,"firstName":"Giulio","lastName":"Larkworthy","dateBirth":"2/25/1952","sex":"M"},
{"id":808,"firstName":"Vivia","lastName":"Josey","dateBirth":"7/19/1983","sex":"F"},
{"id":809,"firstName":"Venus","lastName":"McKue","dateBirth":"1/17/1979","sex":"F"},
{"id":810,"firstName":"Willi","lastName":"Launder","dateBirth":"1/18/1937","sex":"F"},
{"id":811,"firstName":"Nicolas","lastName":"McKeller","dateBirth":"12/21/1997","sex":"M"},
{"id":812,"firstName":"Guendolen","lastName":"Extence","dateBirth":"1/29/1965","sex":"F"},
{"id":813,"firstName":"Burke","lastName":"Dowda","dateBirth":"6/27/1926","sex":"M"},
{"id":814,"firstName":"Marlowe","lastName":"Tolmie","dateBirth":"2/17/1960","sex":"M"},
{"id":815,"firstName":"Sharona","lastName":"Edden","dateBirth":"12/13/1922","sex":"F"},
{"id":816,"firstName":"Hakim","lastName":"Pipworth","dateBirth":"10/5/1914","sex":"M"},
{"id":817,"firstName":"Nancee","lastName":"Czadla","dateBirth":"7/11/1927","sex":"F"},
{"id":818,"firstName":"Ruthy","lastName":"Batchelder","dateBirth":"2/7/1966","sex":"F"},
{"id":819,"firstName":"Peder","lastName":"Idney","dateBirth":"11/3/1912","sex":"M"},
{"id":820,"firstName":"Vernon","lastName":"Gowman","dateBirth":"9/4/1981","sex":"M"},
{"id":821,"firstName":"Gregoire","lastName":"Coenraets","dateBirth":"5/4/1974","sex":"M"},
{"id":822,"firstName":"Bent","lastName":"Farris","dateBirth":"9/6/1972","sex":"M"},
{"id":823,"firstName":"Dannie","lastName":"Tappor","dateBirth":"9/19/1927","sex":"F"},
{"id":824,"firstName":"Bink","lastName":"Eadmeads","dateBirth":"12/6/1982","sex":"M"},
{"id":825,"firstName":"Hayes","lastName":"Aimer","dateBirth":"5/30/1933","sex":"M"},
{"id":826,"firstName":"Avrit","lastName":"Isacq","dateBirth":"4/14/1966","sex":"F"},
{"id":827,"firstName":"Lilyan","lastName":"Boik","dateBirth":"10/21/2004","sex":"F"},
{"id":828,"firstName":"Bartolomeo","lastName":"Jedrzejkiewicz","dateBirth":"12/23/1960","sex":"M"},
{"id":829,"firstName":"Joye","lastName":"Stannering","dateBirth":"8/28/1936","sex":"F"},
{"id":830,"firstName":"Kaitlin","lastName":"Karlolak","dateBirth":"4/16/1942","sex":"F"},
{"id":831,"firstName":"Faythe","lastName":"Stather","dateBirth":"5/15/2004","sex":"F"},
{"id":832,"firstName":"Dominick","lastName":"Goodsir","dateBirth":"6/28/1917","sex":"M"},
{"id":833,"firstName":"Anni","lastName":"Rosenbarg","dateBirth":"6/10/1910","sex":"F"},
{"id":834,"firstName":"Shae","lastName":"McKernan","dateBirth":"8/12/1953","sex":"M"},
{"id":835,"firstName":"Carlo","lastName":"Bedinham","dateBirth":"10/28/1960","sex":"M"},
{"id":836,"firstName":"Richie","lastName":"Gossan","dateBirth":"5/26/2004","sex":"M"},
{"id":837,"firstName":"Ignacio","lastName":"Conn","dateBirth":"7/5/1978","sex":"M"},
{"id":838,"firstName":"Norri","lastName":"Gemnett","dateBirth":"3/31/1991","sex":"F"},
{"id":839,"firstName":"Desiree","lastName":"Dobeson","dateBirth":"12/9/1931","sex":"F"},
{"id":840,"firstName":"Nichole","lastName":"Ashcroft","dateBirth":"2/17/1943","sex":"F"},
{"id":841,"firstName":"Yvon","lastName":"Marian","dateBirth":"10/29/1950","sex":"M"},
{"id":842,"firstName":"Consuelo","lastName":"Mitchley","dateBirth":"3/31/1986","sex":"F"},
{"id":843,"firstName":"Cthrine","lastName":"Gummery","dateBirth":"9/20/1905","sex":"F"},
{"id":844,"firstName":"Lynnett","lastName":"Bithell","dateBirth":"8/31/1995","sex":"F"},
{"id":845,"firstName":"Oralie","lastName":"McGinn","dateBirth":"4/4/1976","sex":"F"},
{"id":846,"firstName":"Grantham","lastName":"Leming","dateBirth":"7/19/1988","sex":"M"},
{"id":847,"firstName":"Yasmin","lastName":"Albrecht","dateBirth":"11/30/1962","sex":"F"},
{"id":848,"firstName":"Rodd","lastName":"Greenin","dateBirth":"5/17/1910","sex":"M"},
{"id":849,"firstName":"Guillermo","lastName":"Kinnie","dateBirth":"6/14/1945","sex":"M"},
{"id":850,"firstName":"Revkah","lastName":"Kingzet","dateBirth":"1/28/2004","sex":"F"},
{"id":851,"firstName":"Shaylyn","lastName":"Elies","dateBirth":"11/29/1962","sex":"F"},
{"id":852,"firstName":"Marice","lastName":"Lombardo","dateBirth":"9/26/1963","sex":"F"},
{"id":853,"firstName":"Dickie","lastName":"Thunnerclef","dateBirth":"1/1/1937","sex":"M"},
{"id":854,"firstName":"Harriett","lastName":"Cox","dateBirth":"2/23/1957","sex":"F"},
{"id":855,"firstName":"Junia","lastName":"Kimbury","dateBirth":"7/21/1924","sex":"F"},
{"id":856,"firstName":"Deloria","lastName":"Dunseath","dateBirth":"6/20/1940","sex":"F"},
{"id":857,"firstName":"Lothario","lastName":"Winstone","dateBirth":"9/12/1982","sex":"M"},
{"id":858,"firstName":"Bunny","lastName":"Boykett","dateBirth":"11/21/1932","sex":"F"},
{"id":859,"firstName":"Bronnie","lastName":"Cristofor","dateBirth":"3/11/1922","sex":"M"},
{"id":860,"firstName":"Orel","lastName":"Northway","dateBirth":"1/15/1981","sex":"F"},
{"id":861,"firstName":"Matty","lastName":"Peltz","dateBirth":"7/15/1993","sex":"F"},
{"id":862,"firstName":"Nickolaus","lastName":"Champness","dateBirth":"5/5/2002","sex":"M"},
{"id":863,"firstName":"Giff","lastName":"Illiston","dateBirth":"10/24/1920","sex":"M"},
{"id":864,"firstName":"Flora","lastName":"Ruspine","dateBirth":"4/10/1919","sex":"F"},
{"id":865,"firstName":"Uriel","lastName":"Hessentaler","dateBirth":"3/5/1911","sex":"M"},
{"id":866,"firstName":"Farra","lastName":"Ketteman","dateBirth":"1/21/1931","sex":"F"},
{"id":867,"firstName":"Hettie","lastName":"Boxhill","dateBirth":"2/8/1980","sex":"F"},
{"id":868,"firstName":"Mercie","lastName":"Hawson","dateBirth":"5/28/1981","sex":"F"},
{"id":869,"firstName":"Gifford","lastName":"Hindsberg","dateBirth":"12/7/1969","sex":"M"},
{"id":870,"firstName":"Benedetto","lastName":"Shuttlewood","dateBirth":"10/18/1942","sex":"M"},
{"id":871,"firstName":"Alastair","lastName":"Mulgrew","dateBirth":"1/4/1905","sex":"M"},
{"id":872,"firstName":"Almeta","lastName":"Felten","dateBirth":"8/4/1984","sex":"F"},
{"id":873,"firstName":"Reggie","lastName":"Height","dateBirth":"2/1/1978","sex":"F"},
{"id":874,"firstName":"Myer","lastName":"Lavall","dateBirth":"2/16/1923","sex":"M"},
{"id":875,"firstName":"Corrianne","lastName":"Licciardo","dateBirth":"6/12/1944","sex":"F"},
{"id":876,"firstName":"Caresse","lastName":"Blucher","dateBirth":"11/24/1910","sex":"F"},
{"id":877,"firstName":"Hervey","lastName":"Mowsley","dateBirth":"9/1/1938","sex":"M"},
{"id":878,"firstName":"Vachel","lastName":"Chatt","dateBirth":"6/1/1959","sex":"M"},
{"id":879,"firstName":"Meggi","lastName":"Denes","dateBirth":"3/7/1909","sex":"F"},
{"id":880,"firstName":"Meridith","lastName":"Longmire","dateBirth":"3/18/1999","sex":"F"},
{"id":881,"firstName":"Mady","lastName":"Slight","dateBirth":"6/23/1985","sex":"F"},
{"id":882,"firstName":"Ritchie","lastName":"Lambell","dateBirth":"8/7/1944","sex":"M"},
{"id":883,"firstName":"Bernice","lastName":"Geffe","dateBirth":"12/13/1996","sex":"F"},
{"id":884,"firstName":"Chloe","lastName":"Barttrum","dateBirth":"1/22/1989","sex":"F"},
{"id":885,"firstName":"Laurence","lastName":"Clawley","dateBirth":"9/7/1963","sex":"M"},
{"id":886,"firstName":"Cobb","lastName":"Guterson","dateBirth":"8/19/1924","sex":"M"},
{"id":887,"firstName":"Ediva","lastName":"Reardon","dateBirth":"8/4/1957","sex":"F"},
{"id":888,"firstName":"Jone","lastName":"Pitbladdo","dateBirth":"8/19/1907","sex":"M"},
{"id":889,"firstName":"Lorne","lastName":"Lamport","dateBirth":"12/30/1932","sex":"M"},
{"id":890,"firstName":"Myrilla","lastName":"Flux","dateBirth":"9/26/1963","sex":"F"},
{"id":891,"firstName":"Wolf","lastName":"Bartrum","dateBirth":"2/7/1912","sex":"M"},
{"id":892,"firstName":"Mayer","lastName":"Attaway","dateBirth":"10/30/1997","sex":"M"},
{"id":893,"firstName":"Hammad","lastName":"Dunthorn","dateBirth":"6/14/2005","sex":"M"},
{"id":894,"firstName":"Allie","lastName":"Slisby","dateBirth":"10/23/1908","sex":"M"},
{"id":895,"firstName":"Noni","lastName":"Frenchum","dateBirth":"10/13/1938","sex":"F"},
{"id":896,"firstName":"Michal","lastName":"Dowrey","dateBirth":"9/23/1967","sex":"M"},
{"id":897,"firstName":"Wesley","lastName":"Hindmoor","dateBirth":"9/24/1976","sex":"M"},
{"id":898,"firstName":"Una","lastName":"Patmore","dateBirth":"8/24/1962","sex":"F"},
{"id":899,"firstName":"Rand","lastName":"Tonna","dateBirth":"5/14/1926","sex":"M"},
{"id":900,"firstName":"Philis","lastName":"Lindemann","dateBirth":"6/6/1997","sex":"F"},
{"id":901,"firstName":"Scotti","lastName":"Mander","dateBirth":"4/22/1950","sex":"M"},
{"id":902,"firstName":"Roselle","lastName":"Matusson","dateBirth":"5/13/1973","sex":"F"},
{"id":903,"firstName":"Sasha","lastName":"Ferri","dateBirth":"6/25/1974","sex":"M"},
{"id":904,"firstName":"Lefty","lastName":"Gruszecki","dateBirth":"3/28/1976","sex":"M"},
{"id":905,"firstName":"Malva","lastName":"Caverhill","dateBirth":"7/11/1931","sex":"F"},
{"id":906,"firstName":"Ansley","lastName":"Rustadge","dateBirth":"9/25/1951","sex":"F"},
{"id":907,"firstName":"Larry","lastName":"Goman","dateBirth":"6/25/1926","sex":"M"},
{"id":908,"firstName":"Donalt","lastName":"Campione","dateBirth":"1/7/1926","sex":"M"},
{"id":909,"firstName":"Darren","lastName":"Kennett","dateBirth":"4/18/1990","sex":"M"},
{"id":910,"firstName":"Hy","lastName":"Beverley","dateBirth":"11/22/1954","sex":"M"},
{"id":911,"firstName":"Genni","lastName":"Haysman","dateBirth":"3/15/1945","sex":"F"},
{"id":912,"firstName":"Gaye","lastName":"Eddicott","dateBirth":"12/8/1946","sex":"F"},
{"id":913,"firstName":"Glory","lastName":"Nother","dateBirth":"4/16/1953","sex":"F"},
{"id":914,"firstName":"Jasper","lastName":"Livzey","dateBirth":"4/17/1908","sex":"M"},
{"id":915,"firstName":"Stafani","lastName":"Labroue","dateBirth":"9/26/1920","sex":"F"},
{"id":916,"firstName":"Wendel","lastName":"Husby","dateBirth":"10/29/1980","sex":"M"},
{"id":917,"firstName":"Brandtr","lastName":"Camerana","dateBirth":"10/25/1986","sex":"M"},
{"id":918,"firstName":"Delmar","lastName":"Mioni","dateBirth":"6/5/1986","sex":"M"},
{"id":919,"firstName":"Nerte","lastName":"Toll","dateBirth":"12/27/1947","sex":"F"},
{"id":920,"firstName":"Kit","lastName":"Paylor","dateBirth":"5/9/2001","sex":"F"},
{"id":921,"firstName":"Rudiger","lastName":"Bondar","dateBirth":"4/26/1952","sex":"M"},
{"id":922,"firstName":"Jules","lastName":"Ferroni","dateBirth":"6/19/1931","sex":"M"},
{"id":923,"firstName":"Gale","lastName":"Choake","dateBirth":"5/2/1943","sex":"F"},
{"id":924,"firstName":"Basilius","lastName":"Meriott","dateBirth":"6/24/1915","sex":"M"},
{"id":925,"firstName":"Ham","lastName":"Smallacombe","dateBirth":"1/30/1962","sex":"M"},
{"id":926,"firstName":"Aurelea","lastName":"Shout","dateBirth":"11/19/1910","sex":"F"},
{"id":927,"firstName":"Lilas","lastName":"Bennell","dateBirth":"9/8/1996","sex":"F"},
{"id":928,"firstName":"Eziechiele","lastName":"Castellini","dateBirth":"10/1/1999","sex":"M"},
{"id":929,"firstName":"Shae","lastName":"Bebis","dateBirth":"1/10/1993","sex":"M"},
{"id":930,"firstName":"Siouxie","lastName":"Swateridge","dateBirth":"10/31/1979","sex":"F"},
{"id":931,"firstName":"Cesare","lastName":"Grumble","dateBirth":"7/1/1948","sex":"M"},
{"id":932,"firstName":"Ortensia","lastName":"Draper","dateBirth":"7/24/1939","sex":"F"},
{"id":933,"firstName":"Sargent","lastName":"Sobczak","dateBirth":"9/3/1949","sex":"M"},
{"id":934,"firstName":"Layney","lastName":"Keating","dateBirth":"12/12/1954","sex":"F"},
{"id":935,"firstName":"Rod","lastName":"Jamary","dateBirth":"12/21/1919","sex":"M"},
{"id":936,"firstName":"Teador","lastName":"Ceschi","dateBirth":"6/9/1931","sex":"M"},
{"id":937,"firstName":"Stacie","lastName":"Hellewell","dateBirth":"12/12/1997","sex":"F"},
{"id":938,"firstName":"Robinet","lastName":"Oddy","dateBirth":"2/7/1908","sex":"M"},
{"id":939,"firstName":"Martha","lastName":"Denisevich","dateBirth":"3/14/1993","sex":"F"},
{"id":940,"firstName":"Eugenio","lastName":"Rewbottom","dateBirth":"12/4/1967","sex":"M"},
{"id":941,"firstName":"Olympe","lastName":"Cescot","dateBirth":"12/23/1920","sex":"F"},
{"id":942,"firstName":"Osbourne","lastName":"Balcon","dateBirth":"1/6/1931","sex":"M"},
{"id":943,"firstName":"Kristo","lastName":"Fabbro","dateBirth":"3/13/1969","sex":"M"},
{"id":944,"firstName":"Hester","lastName":"Westoff","dateBirth":"7/18/1935","sex":"F"},
{"id":945,"firstName":"Jeddy","lastName":"Wibberley","dateBirth":"9/20/2002","sex":"M"},
{"id":946,"firstName":"Ephrem","lastName":"Wille","dateBirth":"6/18/1967","sex":"M"},
{"id":947,"firstName":"Gallagher","lastName":"Bruin","dateBirth":"7/29/1940","sex":"M"},
{"id":948,"firstName":"Gerta","lastName":"Rubinfajn","dateBirth":"8/17/1976","sex":"F"},
{"id":949,"firstName":"Fonsie","lastName":"Collet","dateBirth":"10/29/1918","sex":"M"},
{"id":950,"firstName":"Meade","lastName":"McIllroy","dateBirth":"9/17/1958","sex":"M"},
{"id":951,"firstName":"Ramsey","lastName":"Mc Ilwrick","dateBirth":"11/5/1908","sex":"M"},
{"id":952,"firstName":"Millard","lastName":"Pinor","dateBirth":"4/19/1995","sex":"M"},
{"id":953,"firstName":"Carolynn","lastName":"Geertje","dateBirth":"6/8/1973","sex":"F"},
{"id":954,"firstName":"Glynis","lastName":"Espino","dateBirth":"7/16/1912","sex":"F"},
{"id":955,"firstName":"Monro","lastName":"Ferronier","dateBirth":"5/24/1951","sex":"M"},
{"id":956,"firstName":"Emory","lastName":"Kobes","dateBirth":"4/2/1981","sex":"M"},
{"id":957,"firstName":"Cymbre","lastName":"Leneve","dateBirth":"3/28/1915","sex":"F"},
{"id":958,"firstName":"Caritta","lastName":"Lillecrop","dateBirth":"1/9/1909","sex":"F"},
{"id":959,"firstName":"Jefferson","lastName":"Whitham","dateBirth":"1/29/1976","sex":"M"},
{"id":960,"firstName":"Skippy","lastName":"McConigal","dateBirth":"10/25/1914","sex":"M"},
{"id":961,"firstName":"Tabby","lastName":"Sylvaine","dateBirth":"5/1/1960","sex":"F"},
{"id":962,"firstName":"Nessie","lastName":"Gilleson","dateBirth":"6/15/1933","sex":"F"},
{"id":963,"firstName":"Reid","lastName":"Abbotson","dateBirth":"7/10/1991","sex":"M"},
{"id":964,"firstName":"Coreen","lastName":"Vennings","dateBirth":"4/26/1956","sex":"F"},
{"id":965,"firstName":"Camila","lastName":"Ennor","dateBirth":"1/18/1940","sex":"F"},
{"id":966,"firstName":"Kellyann","lastName":"Jenteau","dateBirth":"6/23/1961","sex":"F"},
{"id":967,"firstName":"Averell","lastName":"Boxhall","dateBirth":"4/30/1964","sex":"M"},
{"id":968,"firstName":"Gilbertine","lastName":"Petley","dateBirth":"3/16/1913","sex":"F"},
{"id":969,"firstName":"Calv","lastName":"Mival","dateBirth":"1/29/1923","sex":"M"},
{"id":970,"firstName":"Auria","lastName":"Tarbox","dateBirth":"7/8/1984","sex":"F"},
{"id":971,"firstName":"Jere","lastName":"Dominiak","dateBirth":"10/16/1966","sex":"M"},
{"id":972,"firstName":"Shadow","lastName":"Kynastone","dateBirth":"9/5/1927","sex":"M"},
{"id":973,"firstName":"Sherry","lastName":"Fletham","dateBirth":"2/11/1910","sex":"F"},
{"id":974,"firstName":"Janaya","lastName":"MacPaik","dateBirth":"1/6/1983","sex":"F"},
{"id":975,"firstName":"Antoinette","lastName":"Dysert","dateBirth":"1/18/1975","sex":"F"},
{"id":976,"firstName":"Selby","lastName":"McQuin","dateBirth":"5/31/2001","sex":"M"},
{"id":977,"firstName":"Ibbie","lastName":"Aim","dateBirth":"1/11/1958","sex":"F"},
{"id":978,"firstName":"Vachel","lastName":"Alvaro","dateBirth":"7/2/1987","sex":"M"},
{"id":979,"firstName":"Glad","lastName":"Byne","dateBirth":"3/28/2002","sex":"F"},
{"id":980,"firstName":"Sheri","lastName":"Benham","dateBirth":"6/14/1996","sex":"F"},
{"id":981,"firstName":"Alida","lastName":"Tanguy","dateBirth":"10/18/1986","sex":"F"},
{"id":982,"firstName":"Goddart","lastName":"Dupree","dateBirth":"7/29/1966","sex":"M"},
{"id":983,"firstName":"Carolus","lastName":"Halwill","dateBirth":"11/21/1927","sex":"M"},
{"id":984,"firstName":"Derwin","lastName":"Tallet","dateBirth":"11/7/1989","sex":"M"},
{"id":985,"firstName":"Correy","lastName":"McAviy","dateBirth":"8/9/1957","sex":"M"},
{"id":986,"firstName":"Gabriel","lastName":"Habishaw","dateBirth":"6/24/1910","sex":"M"},
{"id":987,"firstName":"Cara","lastName":"McGoogan","dateBirth":"1/14/1973","sex":"F"},
{"id":988,"firstName":"Tobi","lastName":"Tanby","dateBirth":"4/17/1968","sex":"F"},
{"id":989,"firstName":"Inge","lastName":"Gumly","dateBirth":"5/25/1983","sex":"F"},
{"id":990,"firstName":"Rosella","lastName":"Crosfeld","dateBirth":"9/6/1932","sex":"F"},
{"id":991,"firstName":"Rusty","lastName":"Mulbery","dateBirth":"12/20/1999","sex":"M"},
{"id":992,"firstName":"Felipe","lastName":"Girardot","dateBirth":"2/9/1995","sex":"M"},
{"id":993,"firstName":"Thibaut","lastName":"MacPharlain","dateBirth":"10/19/1939","sex":"M"},
{"id":994,"firstName":"Seth","lastName":"Lelliott","dateBirth":"1/8/1992","sex":"M"},
{"id":995,"firstName":"Kaleb","lastName":"Tobin","dateBirth":"1/18/1993","sex":"M"},
{"id":996,"firstName":"Penn","lastName":"Longfellow","dateBirth":"1/23/1975","sex":"M"},
{"id":997,"firstName":"Tiphani","lastName":"McWaters","dateBirth":"3/28/1923","sex":"F"},
{"id":998,"firstName":"Cammy","lastName":"Bohlens","dateBirth":"6/22/1964","sex":"M"},
{"id":999,"firstName":"Sissie","lastName":"Pannett","dateBirth":"12/17/1924","sex":"F"},
{"id":1000,"firstName":"Murray","lastName":"McAloren","dateBirth":"5/18/2000","sex":"M"}]}